[{"id":1169,"verse_number":9,"verse_key":"8:9","hizb_number":18,"rub_el_hizb_number":71,"ruku_number":146,"manzil_number":2,"sajdah_number":null,"text_qpc_hafs":"إِذۡ تَسۡتَغِيثُونَ رَبَّكُمۡ فَٱسۡتَجَابَ لَكُمۡ أَنِّي مُمِدُّكُم بِأَلۡفٖ مِّنَ ٱلۡمَلَٰٓئِكَةِ مُرۡدِفِينَ ٩","text_uthmani":"إِذْ تَسْتَغِيثُونَ رَبَّكُمْ فَٱسْتَجَابَ لَكُمْ أَنِّى مُمِدُّكُم بِأَلْفٍ مِّنَ ٱلْمَلَـٰٓئِكَةِ مُرْدِفِينَ","page_number":178,"juz_number":9,"words":[{"id":9940,"position":1,"audio_url":"wbw/008_009_001.mp3","char_type_name":"word","text_qpc_hafs":"إِذۡ","text_uthmani":"إِذْ","line_number":1,"text_uthmani_tajweed":"إِذۡ","page_number":178,"text":"إِذْ","translation":{"text":"When","language_name":"english"},"transliteration":{"text":"idh","language_name":"english"}},{"id":9941,"position":2,"audio_url":"wbw/008_009_002.mp3","char_type_name":"word","text_qpc_hafs":"تَسۡتَغِيثُونَ","text_uthmani":"تَسْتَغِيثُونَ","line_number":1,"text_uthmani_tajweed":"تَسۡتَغِيثُونَ","page_number":178,"text":"تَسْتَغِيثُونَ","translation":{"text":"you were seeking help","language_name":"english"},"transliteration":{"text":"tastaghīthūna","language_name":"english"}},{"id":9942,"position":3,"audio_url":"wbw/008_009_003.mp3","char_type_name":"word","text_qpc_hafs":"رَبَّكُمۡ","text_uthmani":"رَبَّكُمْ","line_number":1,"text_uthmani_tajweed":"رَبَّكُمۡ","page_number":178,"text":"رَبَّكُمْ","translation":{"text":"(of) your Lord","language_name":"english"},"transliteration":{"text":"rabbakum","language_name":"english"}},{"id":9943,"position":4,"audio_url":"wbw/008_009_004.mp3","char_type_name":"word","text_qpc_hafs":"فَٱسۡتَجَابَ","text_uthmani":"فَٱسْتَجَابَ","line_number":1,"text_uthmani_tajweed":"فَ<rule class=ham_wasl>ٱ</rule>سۡتَجَابَ","page_number":178,"text":"فَٱسْتَجَابَ","translation":{"text":"and He answered","language_name":"english"},"transliteration":{"text":"fa-is'tajāba","language_name":"english"}},{"id":9944,"position":5,"audio_url":"wbw/008_009_005.mp3","char_type_name":"word","text_qpc_hafs":"لَكُمۡ","text_uthmani":"لَكُمْ","line_number":1,"text_uthmani_tajweed":"لَكُمۡ","page_number":178,"text":"لَكُمْ","translation":{"text":"[to] you","language_name":"english"},"transliteration":{"text":"lakum","language_name":"english"}},{"id":9945,"position":6,"audio_url":"wbw/008_009_006.mp3","char_type_name":"word","text_qpc_hafs":"أَنِّي","text_uthmani":"أَنِّى","line_number":1,"text_uthmani_tajweed":"أَ<rule class=ghunnah>نّ</rule>ِى","page_number":178,"text":"أَنِّى","translation":{"text":"Indeed, I am","language_name":"english"},"transliteration":{"text":"annī","language_name":"english"}},{"id":9946,"position":7,"audio_url":"wbw/008_009_007.mp3","char_type_name":"word","text_qpc_hafs":"مُمِدُّكُم","text_uthmani":"مُمِدُّكُم","line_number":1,"text_uthmani_tajweed":"مُمِدُّك<rule class=ikhafa_shafawi>ُم</rule>","page_number":178,"text":"مُمِدُّكُم","translation":{"text":"going to reinforce you","language_name":"english"},"transliteration":{"text":"mumiddukum","language_name":"english"}},{"id":9947,"position":8,"audio_url":"wbw/008_009_008.mp3","char_type_name":"word","text_qpc_hafs":"بِأَلۡفٖ","text_uthmani":"بِأَلْفٍۢ","line_number":1,"text_uthmani_tajweed":"<rule class=ikhafa_shafawi>ب</rule>ِأَلۡ<rule class=idgham_ghunnah>فٍ</rule>","page_number":178,"text":"بِأَلْفٍۢ","translation":{"text":"with a thousand","language_name":"english"},"transliteration":{"text":"bi-alfin","language_name":"english"}},{"id":9948,"position":9,"audio_url":"wbw/008_009_009.mp3","char_type_name":"word","text_qpc_hafs":"مِّنَ","text_uthmani":"مِّنَ","line_number":2,"text_uthmani_tajweed":"<rule class=idgham_ghunnah>م</rule>ِّنَ","page_number":178,"text":"مِّنَ","translation":{"text":"of","language_name":"english"},"transliteration":{"text":"mina","language_name":"english"}},{"id":9949,"position":10,"audio_url":"wbw/008_009_010.mp3","char_type_name":"word","text_qpc_hafs":"ٱلۡمَلَٰٓئِكَةِ","text_uthmani":"ٱلْمَلَـٰٓئِكَةِ","line_number":2,"text_uthmani_tajweed":"<rule class=ham_wasl>ٱ</rule>لۡمَلَ<rule class=madda_obligatory_mottasel>ـٰٓ</rule>ئِكَةِ","page_number":178,"text":"ٱلْمَلَـٰٓئِكَةِ","translation":{"text":"the Angels","language_name":"english"},"transliteration":{"text":"l-malāikati","language_name":"english"}},{"id":9950,"position":11,"audio_url":"wbw/008_009_011.mp3","char_type_name":"word","text_qpc_hafs":"مُرۡدِفِينَ","text_uthmani":"مُرْدِفِينَ","line_number":2,"text_uthmani_tajweed":"مُرۡدِف<rule class=madda_permissible>ِي</rule>نَ","page_number":178,"text":"مُرْدِفِينَ","translation":{"text":"one after another","language_name":"english"},"transliteration":{"text":"mur'difīna","language_name":"english"}},{"id":9951,"position":12,"audio_url":null,"char_type_name":"end","text_qpc_hafs":"٩","text_uthmani":"٩","line_number":2,"text_uthmani_tajweed":"٩","page_number":178,"text":"٩","translation":{"text":"(9)","language_name":"english"},"transliteration":{"text":null,"language_name":"english"}}],"audio":{"url":"Alafasy/mp3/008009.mp3","segments":[[0,1,50,350],[1,2,360,2160],[2,3,2170,3220],[3,4,3230,4580],[4,5,4590,5270],[5,6,5280,7090],[6,7,7100,9070],[7,8,9080,10800],[8,9,10810,11170],[9,10,11180,14240],[10,11,14250,16530]]},"translations":[{"id":402872,"resource_id":85,"text":"When you begged your Lord for help, He answered you, ‘I will reinforce you with a thousand angels in succession.’"}]},{"id":1170,"verse_number":10,"verse_key":"8:10","hizb_number":18,"rub_el_hizb_number":71,"ruku_number":146,"manzil_number":2,"sajdah_number":null,"text_qpc_hafs":"وَمَا جَعَلَهُ ٱللَّهُ إِلَّا بُشۡرَىٰ وَلِتَطۡمَئِنَّ بِهِۦ قُلُوبُكُمۡۚ وَمَا ٱلنَّصۡرُ إِلَّا مِنۡ عِندِ ٱللَّهِۚ إِنَّ ٱللَّهَ عَزِيزٌ حَكِيمٌ ١٠","text_uthmani":"وَمَا جَعَلَهُ ٱللَّهُ إِلَّا بُشْرَىٰ وَلِتَطْمَئِنَّ بِهِۦ قُلُوبُكُمْ ۚ وَمَا ٱلنَّصْرُ إِلَّا مِنْ عِندِ ٱللَّهِ ۚ إِنَّ ٱللَّهَ عَزِيزٌ حَكِيمٌ","page_number":178,"juz_number":9,"words":[{"id":11134,"position":1,"audio_url":"wbw/008_010_001.mp3","char_type_name":"word","text_qpc_hafs":"وَمَا","text_uthmani":"وَمَا","line_number":2,"text_uthmani_tajweed":"وَمَا","page_number":178,"text":"وَمَا","translation":{"text":"And not","language_name":"english"},"transliteration":{"text":"wamā","language_name":"english"}},{"id":11135,"position":2,"audio_url":"wbw/008_010_002.mp3","char_type_name":"word","text_qpc_hafs":"جَعَلَهُ","text_uthmani":"جَعَلَهُ","line_number":2,"text_uthmani_tajweed":"جَعَلَهُ","page_number":178,"text":"جَعَلَهُ","translation":{"text":"(it was) made","language_name":"english"},"transliteration":{"text":"jaʿalahu","language_name":"english"}},{"id":11136,"position":3,"audio_url":"wbw/008_010_003.mp3","char_type_name":"word","text_qpc_hafs":"ٱللَّهُ","text_uthmani":"ٱللَّهُ","line_number":2,"text_uthmani_tajweed":"<rule class=ham_wasl>ٱ</rule>للَّهُ","page_number":178,"text":"ٱللَّهُ","translation":{"text":"(by) Allah","language_name":"english"},"transliteration":{"text":"l-lahu","language_name":"english"}},{"id":11137,"position":4,"audio_url":"wbw/008_010_004.mp3","char_type_name":"word","text_qpc_hafs":"إِلَّا","text_uthmani":"إِلَّا","line_number":2,"text_uthmani_tajweed":"إِلَّا","page_number":178,"text":"إِلَّا","translation":{"text":"but","language_name":"english"},"transliteration":{"text":"illā","language_name":"english"}},{"id":11138,"position":5,"audio_url":"wbw/008_010_005.mp3","char_type_name":"word","text_qpc_hafs":"بُشۡرَىٰ","text_uthmani":"بُشْرَىٰ","line_number":2,"text_uthmani_tajweed":"بُشۡرَىٰ","page_number":178,"text":"بُشْرَىٰ","translation":{"text":"good tidings","language_name":"english"},"transliteration":{"text":"bush'rā","language_name":"english"}},{"id":11139,"position":6,"audio_url":"wbw/008_010_006.mp3","char_type_name":"word","text_qpc_hafs":"وَلِتَطۡمَئِنَّ","text_uthmani":"وَلِتَطْمَئِنَّ","line_number":3,"text_uthmani_tajweed":"وَلِتَ<rule class=qalaqah>طۡ</rule>مَئِ<rule class=ghunnah>نّ</rule>َ","page_number":178,"text":"وَلِتَطْمَئِنَّ","translation":{"text":"and so that might be at rest","language_name":"english"},"transliteration":{"text":"walitaṭma-inna","language_name":"english"}},{"id":11140,"position":7,"audio_url":"wbw/008_010_007.mp3","char_type_name":"word","text_qpc_hafs":"بِهِۦ","text_uthmani":"بِهِۦ","line_number":3,"text_uthmani_tajweed":"بِه<rule class=madda_normal>ِۦ</rule>","page_number":178,"text":"بِهِۦ","translation":{"text":"with it","language_name":"english"},"transliteration":{"text":"bihi","language_name":"english"}},{"id":11141,"position":8,"audio_url":"wbw/008_010_008.mp3","char_type_name":"word","text_qpc_hafs":"قُلُوبُكُمۡۚ","text_uthmani":"قُلُوبُكُمْ ۚ","line_number":3,"text_uthmani_tajweed":"قُلُوبُكُمۡ‌ۚ","page_number":178,"text":"قُلُوبُكُمْ ۚ","translation":{"text":"your hearts","language_name":"english"},"transliteration":{"text":"qulūbukum","language_name":"english"}},{"id":11143,"position":9,"audio_url":"wbw/008_010_010.mp3","char_type_name":"word","text_qpc_hafs":"وَمَا","text_uthmani":"وَمَا","line_number":3,"text_uthmani_tajweed":"وَمَا","page_number":178,"text":"وَمَا","translation":{"text":"And (there is) no","language_name":"english"},"transliteration":{"text":"wamā","language_name":"english"}},{"id":11144,"position":10,"audio_url":"wbw/008_010_011.mp3","char_type_name":"word","text_qpc_hafs":"ٱلنَّصۡرُ","text_uthmani":"ٱلنَّصْرُ","line_number":3,"text_uthmani_tajweed":"<rule class=ham_wasl>ٱ</rule><rule class=laam_shamsiyah>ل</rule><rule class=ghunnah>نّ</rule>َصۡرُ","page_number":178,"text":"ٱلنَّصْرُ","translation":{"text":"[the] victory","language_name":"english"},"transliteration":{"text":"l-naṣru","language_name":"english"}},{"id":11145,"position":11,"audio_url":"wbw/008_010_012.mp3","char_type_name":"word","text_qpc_hafs":"إِلَّا","text_uthmani":"إِلَّا","line_number":3,"text_uthmani_tajweed":"إِلَّا","page_number":178,"text":"إِلَّا","translation":{"text":"except","language_name":"english"},"transliteration":{"text":"illā","language_name":"english"}},{"id":11146,"position":12,"audio_url":"wbw/008_010_013.mp3","char_type_name":"word","text_qpc_hafs":"مِنۡ","text_uthmani":"مِنْ","line_number":3,"text_uthmani_tajweed":"مِنۡ","page_number":178,"text":"مِنْ","translation":{"text":"from","language_name":"english"},"transliteration":{"text":"min","language_name":"english"}},{"id":11147,"position":13,"audio_url":"wbw/008_010_014.mp3","char_type_name":"word","text_qpc_hafs":"عِندِ","text_uthmani":"عِندِ","line_number":3,"text_uthmani_tajweed":"عِ<rule class=ikhafa>ند</rule>ِ","page_number":178,"text":"عِندِ","translation":{"text":"[of]","language_name":"english"},"transliteration":{"text":"ʿindi","language_name":"english"}},{"id":11148,"position":14,"audio_url":"wbw/008_010_015.mp3","char_type_name":"word","text_qpc_hafs":"ٱللَّهِۚ","text_uthmani":"ٱللَّهِ ۚ","line_number":3,"text_uthmani_tajweed":"<rule class=ham_wasl>ٱ</rule>للَّهِ‌ۚ","page_number":178,"text":"ٱللَّهِ ۚ","translation":{"text":"Allah","language_name":"english"},"transliteration":{"text":"l-lahi","language_name":"english"}},{"id":11150,"position":15,"audio_url":"wbw/008_010_017.mp3","char_type_name":"word","text_qpc_hafs":"إِنَّ","text_uthmani":"إِنَّ","line_number":3,"text_uthmani_tajweed":"إِ<rule class=ghunnah>نّ</rule>َ","page_number":178,"text":"إِنَّ","translation":{"text":"Indeed","language_name":"english"},"transliteration":{"text":"inna","language_name":"english"}},{"id":11151,"position":16,"audio_url":"wbw/008_010_018.mp3","char_type_name":"word","text_qpc_hafs":"ٱللَّهَ","text_uthmani":"ٱللَّهَ","line_number":3,"text_uthmani_tajweed":"<rule class=ham_wasl>ٱ</rule>للَّهَ","page_number":178,"text":"ٱللَّهَ","translation":{"text":"Allah","language_name":"english"},"transliteration":{"text":"l-laha","language_name":"english"}},{"id":11152,"position":17,"audio_url":"wbw/008_010_019.mp3","char_type_name":"word","text_qpc_hafs":"عَزِيزٌ","text_uthmani":"عَزِيزٌ","line_number":4,"text_uthmani_tajweed":"عَزِيزٌ","page_number":178,"text":"عَزِيزٌ","translation":{"text":"(is) All-Mighty","language_name":"english"},"transliteration":{"text":"ʿazīzun","language_name":"english"}},{"id":11153,"position":18,"audio_url":"wbw/008_010_020.mp3","char_type_name":"word","text_qpc_hafs":"حَكِيمٌ","text_uthmani":"حَكِيمٌ","line_number":4,"text_uthmani_tajweed":"حَك<rule class=madda_permissible>ِي</rule>مٌ","page_number":178,"text":"حَكِيمٌ","translation":{"text":"All-Wise","language_name":"english"},"transliteration":{"text":"ḥakīmun","language_name":"english"}},{"id":11154,"position":19,"audio_url":null,"char_type_name":"end","text_qpc_hafs":"١٠","text_uthmani":"١٠","line_number":4,"text_uthmani_tajweed":"١٠","page_number":178,"text":"١٠","translation":{"text":"(10)","language_name":"english"},"transliteration":{"text":null,"language_name":"english"}}],"audio":{"url":"Alafasy/mp3/008010.mp3","segments":[[0,1,30,660],[1,2,670,1710],[2,3,1720,2500],[3,4,2510,3330],[4,5,3340,4280],[5,6,4290,7000],[6,7,7010,7680],[7,8,7690,9490],[8,9,9500,9950],[9,10,9960,11420],[10,11,11430,12300],[11,12,12310,12650],[12,13,12660,14300],[13,14,14310,15000],[14,15,15010,18980],[15,16,18990,19830],[16,17,19840,20990],[17,18,21000,23250]]},"translations":[{"id":402873,"resource_id":85,"text":"God made this a message of hope to reassure your hearts: help comes only from God, He is mighty and wise."}]},{"id":1171,"verse_number":11,"verse_key":"8:11","hizb_number":18,"rub_el_hizb_number":71,"ruku_number":147,"manzil_number":2,"sajdah_number":null,"text_qpc_hafs":"إِذۡ يُغَشِّيكُمُ ٱلنُّعَاسَ أَمَنَةٗ مِّنۡهُ وَيُنَزِّلُ عَلَيۡكُم مِّنَ ٱلسَّمَآءِ مَآءٗ لِّيُطَهِّرَكُم بِهِۦ وَيُذۡهِبَ عَنكُمۡ رِجۡزَ ٱلشَّيۡطَٰنِ وَلِيَرۡبِطَ عَلَىٰ قُلُوبِكُمۡ وَيُثَبِّتَ بِهِ ٱلۡأَقۡدَامَ ١١","text_uthmani":"إِذْ يُغَشِّيكُمُ ٱلنُّعَاسَ أَمَنَةً مِّنْهُ وَيُنَزِّلُ عَلَيْكُم مِّنَ ٱلسَّمَآءِ مَآءً لِّيُطَهِّرَكُم بِهِۦ وَيُذْهِبَ عَنكُمْ رِجْزَ ٱلشَّيْطَـٰنِ وَلِيَرْبِطَ عَلَىٰ قُلُوبِكُمْ وَيُثَبِّتَ بِهِ ٱلْأَقْدَامَ","page_number":178,"juz_number":9,"words":[{"id":12458,"position":1,"audio_url":"wbw/008_011_001.mp3","char_type_name":"word","text_qpc_hafs":"إِذۡ","text_uthmani":"إِذْ","line_number":4,"text_uthmani_tajweed":"إِذۡ","page_number":178,"text":"إِذْ","translation":{"text":"When","language_name":"english"},"transliteration":{"text":"idh","language_name":"english"}},{"id":12459,"position":2,"audio_url":"wbw/008_011_002.mp3","char_type_name":"word","text_qpc_hafs":"يُغَشِّيكُمُ","text_uthmani":"يُغَشِّيكُمُ","line_number":4,"text_uthmani_tajweed":"يُغَشِّيكُمُ","page_number":178,"text":"يُغَشِّيكُمُ","translation":{"text":"He covered you","language_name":"english"},"transliteration":{"text":"yughashīkumu","language_name":"english"}},{"id":12460,"position":3,"audio_url":"wbw/008_011_003.mp3","char_type_name":"word","text_qpc_hafs":"ٱلنُّعَاسَ","text_uthmani":"ٱلنُّعَاسَ","line_number":4,"text_uthmani_tajweed":"<rule class=ham_wasl>ٱ</rule><rule class=laam_shamsiyah>ل</rule><rule class=ghunnah>نّ</rule>ُعَاسَ","page_number":178,"text":"ٱلنُّعَاسَ","translation":{"text":"with [the] slumber","language_name":"english"},"transliteration":{"text":"l-nuʿāsa","language_name":"english"}},{"id":12461,"position":4,"audio_url":"wbw/008_011_004.mp3","char_type_name":"word","text_qpc_hafs":"أَمَنَةٗ","text_uthmani":"أَمَنَةًۭ","line_number":4,"text_uthmani_tajweed":"أَمَنَ<rule class=idgham_ghunnah>ةً</rule>","page_number":178,"text":"أَمَنَةًۭ","translation":{"text":"a security","language_name":"english"},"transliteration":{"text":"amanatan","language_name":"english"}},{"id":12462,"position":5,"audio_url":"wbw/008_011_005.mp3","char_type_name":"word","text_qpc_hafs":"مِّنۡهُ","text_uthmani":"مِّنْهُ","line_number":4,"text_uthmani_tajweed":"<rule class=idgham_ghunnah>م</rule>ِّنۡهُ","page_number":178,"text":"مِّنْهُ","translation":{"text":"from Him","language_name":"english"},"transliteration":{"text":"min'hu","language_name":"english"}},{"id":12463,"position":6,"audio_url":"wbw/008_011_006.mp3","char_type_name":"word","text_qpc_hafs":"وَيُنَزِّلُ","text_uthmani":"وَيُنَزِّلُ","line_number":4,"text_uthmani_tajweed":"وَيُنَزِّلُ","page_number":178,"text":"وَيُنَزِّلُ","translation":{"text":"and sent down","language_name":"english"},"transliteration":{"text":"wayunazzilu","language_name":"english"}},{"id":12464,"position":7,"audio_url":"wbw/008_011_007.mp3","char_type_name":"word","text_qpc_hafs":"عَلَيۡكُم","text_uthmani":"عَلَيْكُم","line_number":5,"text_uthmani_tajweed":"عَلَيۡك<rule class=idgham_shafawi>ُم</rule>","page_number":178,"text":"عَلَيْكُم","translation":{"text":"upon you","language_name":"english"},"transliteration":{"text":"ʿalaykum","language_name":"english"}},{"id":12465,"position":8,"audio_url":"wbw/008_011_008.mp3","char_type_name":"word","text_qpc_hafs":"مِّنَ","text_uthmani":"مِّنَ","line_number":5,"text_uthmani_tajweed":"<rule class=idgham_shafawi>م</rule>ِّنَ","page_number":178,"text":"مِّنَ","translation":{"text":"from","language_name":"english"},"transliteration":{"text":"mina","language_name":"english"}},{"id":12466,"position":9,"audio_url":"wbw/008_011_009.mp3","char_type_name":"word","text_qpc_hafs":"ٱلسَّمَآءِ","text_uthmani":"ٱلسَّمَآءِ","line_number":5,"text_uthmani_tajweed":"<rule class=ham_wasl>ٱ</rule><rule class=laam_shamsiyah>ل</rule>سَّم<rule class=madda_obligatory_mottasel>َا</rule>ٓءِ","page_number":178,"text":"ٱلسَّمَآءِ","translation":{"text":"the sky","language_name":"english"},"transliteration":{"text":"l-samāi","language_name":"english"}},{"id":12467,"position":10,"audio_url":"wbw/008_011_010.mp3","char_type_name":"word","text_qpc_hafs":"مَآءٗ","text_uthmani":"مَآءًۭ","line_number":5,"text_uthmani_tajweed":"م<rule class=madda_obligatory_mottasel>َا</rule>ٓ<rule class=idgham_wo_ghunnah>ءً</rule>","page_number":178,"text":"مَآءًۭ","translation":{"text":"water","language_name":"english"},"transliteration":{"text":"māan","language_name":"english"}},{"id":12468,"position":11,"audio_url":"wbw/008_011_011.mp3","char_type_name":"word","text_qpc_hafs":"لِّيُطَهِّرَكُم","text_uthmani":"لِّيُطَهِّرَكُم","line_number":5,"text_uthmani_tajweed":"<rule class=idgham_wo_ghunnah>ل</rule>ِّيُطَهِّرَك<rule class=ikhafa_shafawi>ُم</rule>","page_number":178,"text":"لِّيُطَهِّرَكُم","translation":{"text":"so that He may purify you","language_name":"english"},"transliteration":{"text":"liyuṭahhirakum","language_name":"english"}},{"id":12469,"position":12,"audio_url":"wbw/008_011_012.mp3","char_type_name":"word","text_qpc_hafs":"بِهِۦ","text_uthmani":"بِهِۦ","line_number":5,"text_uthmani_tajweed":"<rule class=ikhafa_shafawi>ب</rule>ِه<rule class=madda_normal>ِۦ</rule>","page_number":178,"text":"بِهِۦ","translation":{"text":"with it","language_name":"english"},"transliteration":{"text":"bihi","language_name":"english"}},{"id":12470,"position":13,"audio_url":"wbw/008_011_013.mp3","char_type_name":"word","text_qpc_hafs":"وَيُذۡهِبَ","text_uthmani":"وَيُذْهِبَ","line_number":5,"text_uthmani_tajweed":"وَيُذۡهِبَ","page_number":178,"text":"وَيُذْهِبَ","translation":{"text":"and take away","language_name":"english"},"transliteration":{"text":"wayudh'hiba","language_name":"english"}},{"id":12471,"position":14,"audio_url":"wbw/008_011_014.mp3","char_type_name":"word","text_qpc_hafs":"عَنكُمۡ","text_uthmani":"عَنكُمْ","line_number":5,"text_uthmani_tajweed":"عَ<rule class=ikhafa>نك</rule>ُمۡ","page_number":178,"text":"عَنكُمْ","translation":{"text":"from you","language_name":"english"},"transliteration":{"text":"ʿankum","language_name":"english"}},{"id":12472,"position":15,"audio_url":"wbw/008_011_015.mp3","char_type_name":"word","text_qpc_hafs":"رِجۡزَ","text_uthmani":"رِجْزَ","line_number":5,"text_uthmani_tajweed":"رِ<rule class=qalaqah>جۡ</rule>زَ","page_number":178,"text":"رِجْزَ","translation":{"text":"evil (suggestions)","language_name":"english"},"transliteration":{"text":"rij'za","language_name":"english"}},{"id":12473,"position":16,"audio_url":"wbw/008_011_016.mp3","char_type_name":"word","text_qpc_hafs":"ٱلشَّيۡطَٰنِ","text_uthmani":"ٱلشَّيْطَـٰنِ","line_number":6,"text_uthmani_tajweed":"<rule class=ham_wasl>ٱ</rule><rule class=laam_shamsiyah>ل</rule>شَّيۡطَ<rule class=madda_normal>ـٰ</rule>نِ","page_number":178,"text":"ٱلشَّيْطَـٰنِ","translation":{"text":"(of) the Shaitaan","language_name":"english"},"transliteration":{"text":"l-shayṭāni","language_name":"english"}},{"id":12474,"position":17,"audio_url":"wbw/008_011_017.mp3","char_type_name":"word","text_qpc_hafs":"وَلِيَرۡبِطَ","text_uthmani":"وَلِيَرْبِطَ","line_number":6,"text_uthmani_tajweed":"وَلِيَرۡبِطَ","page_number":178,"text":"وَلِيَرْبِطَ","translation":{"text":"And to strengthen","language_name":"english"},"transliteration":{"text":"waliyarbiṭa","language_name":"english"}},{"id":12475,"position":18,"audio_url":"wbw/008_011_018.mp3","char_type_name":"word","text_qpc_hafs":"عَلَىٰ","text_uthmani":"عَلَىٰ","line_number":6,"text_uthmani_tajweed":"عَلَىٰ","page_number":178,"text":"عَلَىٰ","translation":{"text":"[on]","language_name":"english"},"transliteration":{"text":"ʿalā","language_name":"english"}},{"id":12476,"position":19,"audio_url":"wbw/008_011_019.mp3","char_type_name":"word","text_qpc_hafs":"قُلُوبِكُمۡ","text_uthmani":"قُلُوبِكُمْ","line_number":6,"text_uthmani_tajweed":"قُلُوبِكُمۡ","page_number":178,"text":"قُلُوبِكُمْ","translation":{"text":"your hearts","language_name":"english"},"transliteration":{"text":"qulūbikum","language_name":"english"}},{"id":12477,"position":20,"audio_url":"wbw/008_011_020.mp3","char_type_name":"word","text_qpc_hafs":"وَيُثَبِّتَ","text_uthmani":"وَيُثَبِّتَ","line_number":6,"text_uthmani_tajweed":"وَيُثَبِّتَ","page_number":178,"text":"وَيُثَبِّتَ","translation":{"text":"and make firm","language_name":"english"},"transliteration":{"text":"wayuthabbita","language_name":"english"}},{"id":12478,"position":21,"audio_url":"wbw/008_011_021.mp3","char_type_name":"word","text_qpc_hafs":"بِهِ","text_uthmani":"بِهِ","line_number":6,"text_uthmani_tajweed":"بِهِ","page_number":178,"text":"بِهِ","translation":{"text":"with it","language_name":"english"},"transliteration":{"text":"bihi","language_name":"english"}},{"id":12479,"position":22,"audio_url":"wbw/008_011_022.mp3","char_type_name":"word","text_qpc_hafs":"ٱلۡأَقۡدَامَ","text_uthmani":"ٱلْأَقْدَامَ","line_number":6,"text_uthmani_tajweed":"<rule class=ham_wasl>ٱ</rule>لۡأَ<rule class=qalaqah>قۡ</rule>د<rule class=madda_permissible>َا</rule>مَ","page_number":178,"text":"ٱلْأَقْدَامَ","translation":{"text":"your feet","language_name":"english"},"transliteration":{"text":"l-aqdāma","language_name":"english"}},{"id":12480,"position":23,"audio_url":null,"char_type_name":"end","text_qpc_hafs":"١١","text_uthmani":"١١","line_number":6,"text_uthmani_tajweed":"١١","page_number":178,"text":"١١","translation":{"text":"(11)","language_name":"english"},"transliteration":{"text":null,"language_name":"english"}}],"audio":{"url":"Alafasy/mp3/008011.mp3","segments":[[0,1,30,390],[1,2,400,1900],[2,3,1910,3620],[3,4,3630,5520],[4,5,5530,6070],[5,6,6080,7270],[6,7,7280,9170],[7,8,9180,9470],[8,9,9480,12410],[9,10,12420,14600],[10,11,14610,17190],[11,12,17200,17960],[12,13,17970,18980],[13,14,18990,20780],[14,15,20790,21430],[15,16,21440,22830],[16,17,22840,24230],[17,18,24240,24790],[18,19,24800,30310],[19,20,30320,31630],[20,21,31640,32120],[21,22,32130,34260]]},"translations":[{"id":402874,"resource_id":85,"text":"Remember when He gave you sleep as a reassurance from Him, and sent down water from the sky to cleanse you, to remove Satan’s pollution from you, to make your hearts strong and your feet firm."}]},{"id":1172,"verse_number":12,"verse_key":"8:12","hizb_number":18,"rub_el_hizb_number":71,"ruku_number":147,"manzil_number":2,"sajdah_number":null,"text_qpc_hafs":"إِذۡ يُوحِي رَبُّكَ إِلَى ٱلۡمَلَٰٓئِكَةِ أَنِّي مَعَكُمۡ فَثَبِّتُواْ ٱلَّذِينَ ءَامَنُواْۚ سَأُلۡقِي فِي قُلُوبِ ٱلَّذِينَ كَفَرُواْ ٱلرُّعۡبَ فَٱضۡرِبُواْ فَوۡقَ ٱلۡأَعۡنَاقِ وَٱضۡرِبُواْ مِنۡهُمۡ كُلَّ بَنَانٖ ١٢","text_uthmani":"إِذْ يُوحِى رَبُّكَ إِلَى ٱلْمَلَـٰٓئِكَةِ أَنِّى مَعَكُمْ فَثَبِّتُوا۟ ٱلَّذِينَ ءَامَنُوا۟ ۚ سَأُلْقِى فِى قُلُوبِ ٱلَّذِينَ كَفَرُوا۟ ٱلرُّعْبَ فَٱضْرِبُوا۟ فَوْقَ ٱلْأَعْنَاقِ وَٱضْرِبُوا۟ مِنْهُمْ كُلَّ بَنَانٍ","page_number":178,"juz_number":9,"words":[{"id":13772,"position":1,"audio_url":"wbw/008_012_001.mp3","char_type_name":"word","text_qpc_hafs":"إِذۡ","text_uthmani":"إِذْ","line_number":7,"text_uthmani_tajweed":"إِذۡ","page_number":178,"text":"إِذْ","translation":{"text":"When","language_name":"english"},"transliteration":{"text":"idh","language_name":"english"}},{"id":13773,"position":2,"audio_url":"wbw/008_012_002.mp3","char_type_name":"word","text_qpc_hafs":"يُوحِي","text_uthmani":"يُوحِى","line_number":7,"text_uthmani_tajweed":"يُوحِى","page_number":178,"text":"يُوحِى","translation":{"text":"inspired","language_name":"english"},"transliteration":{"text":"yūḥī","language_name":"english"}},{"id":13774,"position":3,"audio_url":"wbw/008_012_003.mp3","char_type_name":"word","text_qpc_hafs":"رَبُّكَ","text_uthmani":"رَبُّكَ","line_number":7,"text_uthmani_tajweed":"رَبُّكَ","page_number":178,"text":"رَبُّكَ","translation":{"text":"your Lord","language_name":"english"},"transliteration":{"text":"rabbuka","language_name":"english"}},{"id":13775,"position":4,"audio_url":"wbw/008_012_004.mp3","char_type_name":"word","text_qpc_hafs":"إِلَى","text_uthmani":"إِلَى","line_number":7,"text_uthmani_tajweed":"إِلَى","page_number":178,"text":"إِلَى","translation":{"text":"to","language_name":"english"},"transliteration":{"text":"ilā","language_name":"english"}},{"id":13776,"position":5,"audio_url":"wbw/008_012_005.mp3","char_type_name":"word","text_qpc_hafs":"ٱلۡمَلَٰٓئِكَةِ","text_uthmani":"ٱلْمَلَـٰٓئِكَةِ","line_number":7,"text_uthmani_tajweed":"<rule class=ham_wasl>ٱ</rule>لۡمَلَ<rule class=madda_obligatory_mottasel>ـٰٓ</rule>ئِكَةِ","page_number":178,"text":"ٱلْمَلَـٰٓئِكَةِ","translation":{"text":"the Angels","language_name":"english"},"transliteration":{"text":"l-malāikati","language_name":"english"}},{"id":13777,"position":6,"audio_url":"wbw/008_012_006.mp3","char_type_name":"word","text_qpc_hafs":"أَنِّي","text_uthmani":"أَنِّى","line_number":7,"text_uthmani_tajweed":"أَ<rule class=ghunnah>نّ</rule>ِى","page_number":178,"text":"أَنِّى","translation":{"text":"I am","language_name":"english"},"transliteration":{"text":"annī","language_name":"english"}},{"id":13778,"position":7,"audio_url":"wbw/008_012_007.mp3","char_type_name":"word","text_qpc_hafs":"مَعَكُمۡ","text_uthmani":"مَعَكُمْ","line_number":7,"text_uthmani_tajweed":"مَعَكُمۡ","page_number":178,"text":"مَعَكُمْ","translation":{"text":"with you","language_name":"english"},"transliteration":{"text":"maʿakum","language_name":"english"}},{"id":13779,"position":8,"audio_url":"wbw/008_012_008.mp3","char_type_name":"word","text_qpc_hafs":"فَثَبِّتُواْ","text_uthmani":"فَثَبِّتُوا۟","line_number":7,"text_uthmani_tajweed":"فَثَبِّتُو<rule class=slnt>اۡ</rule>","page_number":178,"text":"فَثَبِّتُوا۟","translation":{"text":"so strengthen","language_name":"english"},"transliteration":{"text":"fathabbitū","language_name":"english"}},{"id":13780,"position":9,"audio_url":"wbw/008_012_009.mp3","char_type_name":"word","text_qpc_hafs":"ٱلَّذِينَ","text_uthmani":"ٱلَّذِينَ","line_number":7,"text_uthmani_tajweed":"<rule class=ham_wasl>ٱ</rule>لَّذِينَ","page_number":178,"text":"ٱلَّذِينَ","translation":{"text":"those who","language_name":"english"},"transliteration":{"text":"alladhīna","language_name":"english"}},{"id":13781,"position":10,"audio_url":"wbw/008_012_010.mp3","char_type_name":"word","text_qpc_hafs":"ءَامَنُواْۚ","text_uthmani":"ءَامَنُوا۟ ۚ","line_number":7,"text_uthmani_tajweed":"ءَامَنُو<rule class=slnt>اۡ‌ۚ</rule>","page_number":178,"text":"ءَامَنُوا۟ ۚ","translation":{"text":"believed","language_name":"english"},"transliteration":{"text":"āmanū","language_name":"english"}},{"id":13783,"position":11,"audio_url":"wbw/008_012_012.mp3","char_type_name":"word","text_qpc_hafs":"سَأُلۡقِي","text_uthmani":"سَأُلْقِى","line_number":8,"text_uthmani_tajweed":"سَأُلۡقِى","page_number":178,"text":"سَأُلْقِى","translation":{"text":"I will cast","language_name":"english"},"transliteration":{"text":"sa-ul'qī","language_name":"english"}},{"id":13784,"position":12,"audio_url":"wbw/008_012_013.mp3","char_type_name":"word","text_qpc_hafs":"فِي","text_uthmani":"فِى","line_number":8,"text_uthmani_tajweed":"فِى","page_number":178,"text":"فِى","translation":{"text":"in","language_name":"english"},"transliteration":{"text":"fī","language_name":"english"}},{"id":13785,"position":13,"audio_url":"wbw/008_012_014.mp3","char_type_name":"word","text_qpc_hafs":"قُلُوبِ","text_uthmani":"قُلُوبِ","line_number":8,"text_uthmani_tajweed":"قُلُوبِ","page_number":178,"text":"قُلُوبِ","translation":{"text":"(the) hearts","language_name":"english"},"transliteration":{"text":"qulūbi","language_name":"english"}},{"id":13786,"position":14,"audio_url":"wbw/008_012_015.mp3","char_type_name":"word","text_qpc_hafs":"ٱلَّذِينَ","text_uthmani":"ٱلَّذِينَ","line_number":8,"text_uthmani_tajweed":"<rule class=ham_wasl>ٱ</rule>لَّذِينَ","page_number":178,"text":"ٱلَّذِينَ","translation":{"text":"(of) those who","language_name":"english"},"transliteration":{"text":"alladhīna","language_name":"english"}},{"id":13787,"position":15,"audio_url":"wbw/008_012_016.mp3","char_type_name":"word","text_qpc_hafs":"كَفَرُواْ","text_uthmani":"كَفَرُوا۟","line_number":8,"text_uthmani_tajweed":"كَفَرُو<rule class=slnt>اۡ</rule>","page_number":178,"text":"كَفَرُوا۟","translation":{"text":"disbelieved ","language_name":"english"},"transliteration":{"text":"kafarū","language_name":"english"}},{"id":13788,"position":16,"audio_url":"wbw/008_012_017.mp3","char_type_name":"word","text_qpc_hafs":"ٱلرُّعۡبَ","text_uthmani":"ٱلرُّعْبَ","line_number":8,"text_uthmani_tajweed":"<rule class=ham_wasl>ٱ</rule><rule class=laam_shamsiyah>ل</rule>رُّعۡبَ","page_number":178,"text":"ٱلرُّعْبَ","translation":{"text":"the terror","language_name":"english"},"transliteration":{"text":"l-ruʿ'ba","language_name":"english"}},{"id":13789,"position":17,"audio_url":"wbw/008_012_018.mp3","char_type_name":"word","text_qpc_hafs":"فَٱضۡرِبُواْ","text_uthmani":"فَٱضْرِبُوا۟","line_number":8,"text_uthmani_tajweed":"فَ<rule class=ham_wasl>ٱ</rule>ضۡرِبُو<rule class=slnt>اۡ</rule>","page_number":178,"text":"فَٱضْرِبُوا۟","translation":{"text":"so strike","language_name":"english"},"transliteration":{"text":"fa-iḍ'ribū","language_name":"english"}},{"id":13790,"position":18,"audio_url":"wbw/008_012_019.mp3","char_type_name":"word","text_qpc_hafs":"فَوۡقَ","text_uthmani":"فَوْقَ","line_number":8,"text_uthmani_tajweed":"فَوۡقَ","page_number":178,"text":"فَوْقَ","translation":{"text":"above","language_name":"english"},"transliteration":{"text":"fawqa","language_name":"english"}},{"id":13791,"position":19,"audio_url":"wbw/008_012_020.mp3","char_type_name":"word","text_qpc_hafs":"ٱلۡأَعۡنَاقِ","text_uthmani":"ٱلْأَعْنَاقِ","line_number":9,"text_uthmani_tajweed":"<rule class=ham_wasl>ٱ</rule>لۡأَعۡنَاقِ","page_number":178,"text":"ٱلْأَعْنَاقِ","translation":{"text":"the necks","language_name":"english"},"transliteration":{"text":"l-aʿnāqi","language_name":"english"}},{"id":13792,"position":20,"audio_url":"wbw/008_012_021.mp3","char_type_name":"word","text_qpc_hafs":"وَٱضۡرِبُواْ","text_uthmani":"وَٱضْرِبُوا۟","line_number":9,"text_uthmani_tajweed":"وَ<rule class=ham_wasl>ٱ</rule>ضۡرِبُو<rule class=slnt>اۡ</rule>","page_number":178,"text":"وَٱضْرِبُوا۟","translation":{"text":"and strike","language_name":"english"},"transliteration":{"text":"wa-iḍ'ribū","language_name":"english"}},{"id":13793,"position":21,"audio_url":"wbw/008_012_022.mp3","char_type_name":"word","text_qpc_hafs":"مِنۡهُمۡ","text_uthmani":"مِنْهُمْ","line_number":9,"text_uthmani_tajweed":"مِنۡهُمۡ","page_number":178,"text":"مِنْهُمْ","translation":{"text":"from them","language_name":"english"},"transliteration":{"text":"min'hum","language_name":"english"}},{"id":13794,"position":22,"audio_url":"wbw/008_012_023.mp3","char_type_name":"word","text_qpc_hafs":"كُلَّ","text_uthmani":"كُلَّ","line_number":9,"text_uthmani_tajweed":"كُلَّ","page_number":178,"text":"كُلَّ","translation":{"text":"every","language_name":"english"},"transliteration":{"text":"kulla","language_name":"english"}},{"id":13795,"position":23,"audio_url":"wbw/008_012_024.mp3","char_type_name":"word","text_qpc_hafs":"بَنَانٖ","text_uthmani":"بَنَانٍۢ","line_number":9,"text_uthmani_tajweed":"بَن<rule class=madda_permissible>َا</rule>نٍ","page_number":178,"text":"بَنَانٍۢ","translation":{"text":"fingertip[s]","language_name":"english"},"transliteration":{"text":"banānin","language_name":"english"}},{"id":13796,"position":24,"audio_url":null,"char_type_name":"end","text_qpc_hafs":"١٢","text_uthmani":"١٢","line_number":9,"text_uthmani_tajweed":"١٢","page_number":178,"text":"١٢","translation":{"text":"(12)","language_name":"english"},"transliteration":{"text":null,"language_name":"english"}}],"audio":{"url":"Alafasy/mp3/008012.mp3","segments":[[0,1,90,470],[1,2,480,1310],[2,3,1320,2260],[3,4,2270,2670],[4,5,2680,5520],[5,6,5530,7230],[6,7,7240,8130],[7,8,8140,9340],[8,9,9350,10470],[9,10,10480,12270],[10,11,12280,13410],[11,12,13420,13860],[12,13,13870,14810],[13,14,14820,15900],[14,15,15910,16650],[15,16,16660,17490],[16,17,17500,18590],[17,18,18600,19340],[18,19,19350,20770],[19,20,20780,21870],[20,21,21880,22740],[21,22,22750,23460],[22,23,23470,25890]]},"translations":[{"id":402875,"resource_id":85,"text":"Your Lord revealed to the angels: ‘I am with you: give the believers firmness; I shall put terror into the hearts of the disbelievers- strike above their necks and strike all their fingertips.’"}]},{"id":1173,"verse_number":13,"verse_key":"8:13","hizb_number":18,"rub_el_hizb_number":71,"ruku_number":147,"manzil_number":2,"sajdah_number":null,"text_qpc_hafs":"ذَٰلِكَ بِأَنَّهُمۡ شَآقُّواْ ٱللَّهَ وَرَسُولَهُۥۚ وَمَن يُشَاقِقِ ٱللَّهَ وَرَسُولَهُۥ فَإِنَّ ٱللَّهَ شَدِيدُ ٱلۡعِقَابِ ١٣","text_uthmani":"ذَٰلِكَ بِأَنَّهُمْ شَآقُّوا۟ ٱللَّهَ وَرَسُولَهُۥ ۚ وَمَن يُشَاقِقِ ٱللَّهَ وَرَسُولَهُۥ فَإِنَّ ٱللَّهَ شَدِيدُ ٱلْعِقَابِ","page_number":178,"juz_number":9,"words":[{"id":14944,"position":1,"audio_url":"wbw/008_013_001.mp3","char_type_name":"word","text_qpc_hafs":"ذَٰلِكَ","text_uthmani":"ذَٰلِكَ","line_number":9,"text_uthmani_tajweed":"ذ<rule class=madda_normal><rule class=custom-alef-maksora>ٰ</rule></rule>لِكَ","page_number":178,"text":"ذَٰلِكَ","translation":{"text":"That","language_name":"english"},"transliteration":{"text":"dhālika","language_name":"english"}},{"id":14945,"position":2,"audio_url":"wbw/008_013_002.mp3","char_type_name":"word","text_qpc_hafs":"بِأَنَّهُمۡ","text_uthmani":"بِأَنَّهُمْ","line_number":9,"text_uthmani_tajweed":"بِأَ<rule class=ghunnah>نّ</rule>َهُمۡ","page_number":178,"text":"بِأَنَّهُمْ","translation":{"text":"(is) because they","language_name":"english"},"transliteration":{"text":"bi-annahum","language_name":"english"}},{"id":14946,"position":3,"audio_url":"wbw/008_013_003.mp3","char_type_name":"word","text_qpc_hafs":"شَآقُّواْ","text_uthmani":"شَآقُّوا۟","line_number":10,"text_uthmani_tajweed":"ش<rule class=madda_necessary>َا</rule>ٓقُّو<rule class=slnt>اۡ</rule>","page_number":178,"text":"شَآقُّوا۟","translation":{"text":"opposed","language_name":"english"},"transliteration":{"text":"shāqqū","language_name":"english"}},{"id":14947,"position":4,"audio_url":"wbw/008_013_004.mp3","char_type_name":"word","text_qpc_hafs":"ٱللَّهَ","text_uthmani":"ٱللَّهَ","line_number":10,"text_uthmani_tajweed":"<rule class=ham_wasl>ٱ</rule>للَّهَ","page_number":178,"text":"ٱللَّهَ","translation":{"text":"Allah","language_name":"english"},"transliteration":{"text":"l-laha","language_name":"english"}},{"id":14948,"position":5,"audio_url":"wbw/008_013_005.mp3","char_type_name":"word","text_qpc_hafs":"وَرَسُولَهُۥۚ","text_uthmani":"وَرَسُولَهُۥ ۚ","line_number":10,"text_uthmani_tajweed":"وَرَسُولَهُ<rule class=madda_normal>ۥ</rule>‌ۚ","page_number":178,"text":"وَرَسُولَهُۥ ۚ","translation":{"text":"and His Messenger","language_name":"english"},"transliteration":{"text":"warasūlahu","language_name":"english"}},{"id":14950,"position":6,"audio_url":"wbw/008_013_007.mp3","char_type_name":"word","text_qpc_hafs":"وَمَن","text_uthmani":"وَمَن","line_number":10,"text_uthmani_tajweed":"وَم<rule class=idgham_ghunnah>َن</rule>","page_number":178,"text":"وَمَن","translation":{"text":"And whoever","language_name":"english"},"transliteration":{"text":"waman","language_name":"english"}},{"id":14951,"position":7,"audio_url":"wbw/008_013_008.mp3","char_type_name":"word","text_qpc_hafs":"يُشَاقِقِ","text_uthmani":"يُشَاقِقِ","line_number":10,"text_uthmani_tajweed":"<rule class=idgham_ghunnah>ي</rule>ُشَاقِقِ","page_number":178,"text":"يُشَاقِقِ","translation":{"text":"opposes","language_name":"english"},"transliteration":{"text":"yushāqiqi","language_name":"english"}},{"id":14952,"position":8,"audio_url":"wbw/008_013_009.mp3","char_type_name":"word","text_qpc_hafs":"ٱللَّهَ","text_uthmani":"ٱللَّهَ","line_number":10,"text_uthmani_tajweed":"<rule class=ham_wasl>ٱ</rule>للَّهَ","page_number":178,"text":"ٱللَّهَ","translation":{"text":"Allah","language_name":"english"},"transliteration":{"text":"l-laha","language_name":"english"}},{"id":14953,"position":9,"audio_url":"wbw/008_013_010.mp3","char_type_name":"word","text_qpc_hafs":"وَرَسُولَهُۥ","text_uthmani":"وَرَسُولَهُۥ","line_number":10,"text_uthmani_tajweed":"وَرَسُولَهُ<rule class=madda_normal>ۥ</rule>","page_number":178,"text":"وَرَسُولَهُۥ","translation":{"text":"and His Messenger","language_name":"english"},"transliteration":{"text":"warasūlahu","language_name":"english"}},{"id":14954,"position":10,"audio_url":"wbw/008_013_011.mp3","char_type_name":"word","text_qpc_hafs":"فَإِنَّ","text_uthmani":"فَإِنَّ","line_number":10,"text_uthmani_tajweed":"فَإِ<rule class=ghunnah>نّ</rule>َ","page_number":178,"text":"فَإِنَّ","translation":{"text":"then indeed","language_name":"english"},"transliteration":{"text":"fa-inna","language_name":"english"}},{"id":14955,"position":11,"audio_url":"wbw/008_013_012.mp3","char_type_name":"word","text_qpc_hafs":"ٱللَّهَ","text_uthmani":"ٱللَّهَ","line_number":10,"text_uthmani_tajweed":"<rule class=ham_wasl>ٱ</rule>للَّهَ","page_number":178,"text":"ٱللَّهَ","translation":{"text":"Allah","language_name":"english"},"transliteration":{"text":"l-laha","language_name":"english"}},{"id":14956,"position":12,"audio_url":"wbw/008_013_013.mp3","char_type_name":"word","text_qpc_hafs":"شَدِيدُ","text_uthmani":"شَدِيدُ","line_number":11,"text_uthmani_tajweed":"شَدِيدُ","page_number":178,"text":"شَدِيدُ","translation":{"text":"(is) severe","language_name":"english"},"transliteration":{"text":"shadīdu","language_name":"english"}},{"id":14957,"position":13,"audio_url":"wbw/008_013_014.mp3","char_type_name":"word","text_qpc_hafs":"ٱلۡعِقَابِ","text_uthmani":"ٱلْعِقَابِ","line_number":11,"text_uthmani_tajweed":"<rule class=ham_wasl>ٱ</rule>لۡعِق<rule class=madda_permissible>َا</rule><rule class=qalaqah>ب</rule>ِ","page_number":178,"text":"ٱلْعِقَابِ","translation":{"text":"in [the] penalty","language_name":"english"},"transliteration":{"text":"l-ʿiqābi","language_name":"english"}},{"id":14958,"position":14,"audio_url":null,"char_type_name":"end","text_qpc_hafs":"١٣","text_uthmani":"١٣","line_number":11,"text_uthmani_tajweed":"١٣","page_number":178,"text":"١٣","translation":{"text":"(13)","language_name":"english"},"transliteration":{"text":null,"language_name":"english"}}],"audio":{"url":"Alafasy/mp3/008013.mp3","segments":[[0,1,30,930],[1,2,940,2780],[2,3,2790,6170],[3,4,6180,7070],[4,5,7080,8810],[5,6,8820,10170],[6,7,10180,11280],[7,8,11290,12160],[8,9,12170,13670],[9,10,13680,15140],[10,11,15150,16070],[11,12,16080,17160],[12,13,17170,19830]]},"translations":[{"id":402876,"resource_id":85,"text":"That was because they opposed God and His Messenger, and if anyone opposes God and His Messenger, God punishes them severely-"}]},{"id":1174,"verse_number":14,"verse_key":"8:14","hizb_number":18,"rub_el_hizb_number":71,"ruku_number":147,"manzil_number":2,"sajdah_number":null,"text_qpc_hafs":"ذَٰلِكُمۡ فَذُوقُوهُ وَأَنَّ لِلۡكَٰفِرِينَ عَذَابَ ٱلنَّارِ ١٤","text_uthmani":"ذَٰلِكُمْ فَذُوقُوهُ وَأَنَّ لِلْكَـٰفِرِينَ عَذَابَ ٱلنَّارِ","page_number":178,"juz_number":9,"words":[{"id":16016,"position":1,"audio_url":"wbw/008_014_001.mp3","char_type_name":"word","text_qpc_hafs":"ذَٰلِكُمۡ","text_uthmani":"ذَٰلِكُمْ","line_number":11,"text_uthmani_tajweed":"ذ<rule class=madda_normal><rule class=custom-alef-maksora>ٰ</rule></rule>لِكُمۡ","page_number":178,"text":"ذَٰلِكُمْ","translation":{"text":"That ","language_name":"english"},"transliteration":{"text":"dhālikum","language_name":"english"}},{"id":16017,"position":2,"audio_url":"wbw/008_014_002.mp3","char_type_name":"word","text_qpc_hafs":"فَذُوقُوهُ","text_uthmani":"فَذُوقُوهُ","line_number":11,"text_uthmani_tajweed":"فَذُوقُوهُ","page_number":178,"text":"فَذُوقُوهُ","translation":{"text":"So taste it","language_name":"english"},"transliteration":{"text":"fadhūqūhu","language_name":"english"}},{"id":16018,"position":3,"audio_url":"wbw/008_014_003.mp3","char_type_name":"word","text_qpc_hafs":"وَأَنَّ","text_uthmani":"وَأَنَّ","line_number":11,"text_uthmani_tajweed":"وَأَ<rule class=ghunnah>نّ</rule>َ","page_number":178,"text":"وَأَنَّ","translation":{"text":"And that","language_name":"english"},"transliteration":{"text":"wa-anna","language_name":"english"}},{"id":16019,"position":4,"audio_url":"wbw/008_014_004.mp3","char_type_name":"word","text_qpc_hafs":"لِلۡكَٰفِرِينَ","text_uthmani":"لِلْكَـٰفِرِينَ","line_number":11,"text_uthmani_tajweed":"لِلۡكَ<rule class=madda_normal>ـٰ</rule>فِرِينَ","page_number":178,"text":"لِلْكَـٰفِرِينَ","translation":{"text":"for the disbelievers","language_name":"english"},"transliteration":{"text":"lil'kāfirīna","language_name":"english"}},{"id":16020,"position":5,"audio_url":"wbw/008_014_005.mp3","char_type_name":"word","text_qpc_hafs":"عَذَابَ","text_uthmani":"عَذَابَ","line_number":12,"text_uthmani_tajweed":"عَذَابَ","page_number":178,"text":"عَذَابَ","translation":{"text":"(is the) punishment","language_name":"english"},"transliteration":{"text":"ʿadhāba","language_name":"english"}},{"id":16021,"position":6,"audio_url":"wbw/008_014_006.mp3","char_type_name":"word","text_qpc_hafs":"ٱلنَّارِ","text_uthmani":"ٱلنَّارِ","line_number":12,"text_uthmani_tajweed":"<rule class=ham_wasl>ٱ</rule><rule class=laam_shamsiyah>ل</rule><rule class=ghunnah>نّ</rule><rule class=madda_permissible>َا</rule>رِ","page_number":178,"text":"ٱلنَّارِ","translation":{"text":"(of) the Fire","language_name":"english"},"transliteration":{"text":"l-nāri","language_name":"english"}},{"id":16022,"position":7,"audio_url":null,"char_type_name":"end","text_qpc_hafs":"١٤","text_uthmani":"١٤","line_number":12,"text_uthmani_tajweed":"١٤","page_number":178,"text":"١٤","translation":{"text":"(14)","language_name":"english"},"transliteration":{"text":null,"language_name":"english"}}],"audio":{"url":"Alafasy/mp3/008014.mp3","segments":[[0,1,90,1130],[1,2,1140,2630],[2,3,2640,4380],[3,4,4390,6160],[4,5,6170,7230],[5,6,7240,8570]]},"translations":[{"id":402877,"resource_id":85,"text":"‘That is what you get! Taste that!’––and the torment of the Fire awaits the disbelievers."}]},{"id":1175,"verse_number":15,"verse_key":"8:15","hizb_number":18,"rub_el_hizb_number":71,"ruku_number":147,"manzil_number":2,"sajdah_number":null,"text_qpc_hafs":"يَٰٓأَيُّهَا ٱلَّذِينَ ءَامَنُوٓاْ إِذَا لَقِيتُمُ ٱلَّذِينَ كَفَرُواْ زَحۡفٗا فَلَا تُوَلُّوهُمُ ٱلۡأَدۡبَارَ ١٥","text_uthmani":"يَـٰٓأَيُّهَا ٱلَّذِينَ ءَامَنُوٓا۟ إِذَا لَقِيتُمُ ٱلَّذِينَ كَفَرُوا۟ زَحْفًا فَلَا تُوَلُّوهُمُ ٱلْأَدْبَارَ","page_number":178,"juz_number":9,"words":[{"id":17249,"position":1,"audio_url":"wbw/008_015_001.mp3","char_type_name":"word","text_qpc_hafs":"يَٰٓأَيُّهَا","text_uthmani":"يَـٰٓأَيُّهَا","line_number":12,"text_uthmani_tajweed":"يَ<rule class=madda_obligatory_mottasel>ـٰٓ</rule>أَيُّهَا","page_number":178,"text":"يَـٰٓأَيُّهَا","translation":{"text":"O you","language_name":"english"},"transliteration":{"text":"yāayyuhā","language_name":"english"}},{"id":17250,"position":2,"audio_url":"wbw/008_015_002.mp3","char_type_name":"word","text_qpc_hafs":"ٱلَّذِينَ","text_uthmani":"ٱلَّذِينَ","line_number":12,"text_uthmani_tajweed":"<rule class=ham_wasl>ٱ</rule>لَّذِينَ","page_number":178,"text":"ٱلَّذِينَ","translation":{"text":"who","language_name":"english"},"transliteration":{"text":"alladhīna","language_name":"english"}},{"id":17251,"position":3,"audio_url":"wbw/008_015_003.mp3","char_type_name":"word","text_qpc_hafs":"ءَامَنُوٓاْ","text_uthmani":"ءَامَنُوٓا۟","line_number":12,"text_uthmani_tajweed":"ءَامَن<rule class=madda_obligatory_mottasel>ُوٓ</rule><rule class=slnt>اۡ</rule>","page_number":178,"text":"ءَامَنُوٓا۟","translation":{"text":"believe","language_name":"english"},"transliteration":{"text":"āmanū","language_name":"english"}},{"id":17252,"position":4,"audio_url":"wbw/008_015_004.mp3","char_type_name":"word","text_qpc_hafs":"إِذَا","text_uthmani":"إِذَا","line_number":12,"text_uthmani_tajweed":"إِذَا","page_number":178,"text":"إِذَا","translation":{"text":"When","language_name":"english"},"transliteration":{"text":"idhā","language_name":"english"}},{"id":17253,"position":5,"audio_url":"wbw/008_015_005.mp3","char_type_name":"word","text_qpc_hafs":"لَقِيتُمُ","text_uthmani":"لَقِيتُمُ","line_number":12,"text_uthmani_tajweed":"لَقِيتُمُ","page_number":178,"text":"لَقِيتُمُ","translation":{"text":"you meet","language_name":"english"},"transliteration":{"text":"laqītumu","language_name":"english"}},{"id":17254,"position":6,"audio_url":"wbw/008_015_006.mp3","char_type_name":"word","text_qpc_hafs":"ٱلَّذِينَ","text_uthmani":"ٱلَّذِينَ","line_number":12,"text_uthmani_tajweed":"<rule class=ham_wasl>ٱ</rule>لَّذِينَ","page_number":178,"text":"ٱلَّذِينَ","translation":{"text":"those who","language_name":"english"},"transliteration":{"text":"alladhīna","language_name":"english"}},{"id":17255,"position":7,"audio_url":"wbw/008_015_007.mp3","char_type_name":"word","text_qpc_hafs":"كَفَرُواْ","text_uthmani":"كَفَرُوا۟","line_number":13,"text_uthmani_tajweed":"كَفَرُو<rule class=slnt>اۡ</rule>","page_number":178,"text":"كَفَرُوا۟","translation":{"text":"disbelieve","language_name":"english"},"transliteration":{"text":"kafarū","language_name":"english"}},{"id":17256,"position":8,"audio_url":"wbw/008_015_008.mp3","char_type_name":"word","text_qpc_hafs":"زَحۡفٗا","text_uthmani":"زَحْفًۭا","line_number":13,"text_uthmani_tajweed":"زَحۡ<rule class=ikhafa>فًا</rule>","page_number":178,"text":"زَحْفًۭا","translation":{"text":"advancing","language_name":"english"},"transliteration":{"text":"zaḥfan","language_name":"english"}},{"id":17257,"position":9,"audio_url":"wbw/008_015_009.mp3","char_type_name":"word","text_qpc_hafs":"فَلَا","text_uthmani":"فَلَا","line_number":13,"text_uthmani_tajweed":"<rule class=ikhafa>ف</rule>َلَا","page_number":178,"text":"فَلَا","translation":{"text":"then (do) not","language_name":"english"},"transliteration":{"text":"falā","language_name":"english"}},{"id":17258,"position":10,"audio_url":"wbw/008_015_010.mp3","char_type_name":"word","text_qpc_hafs":"تُوَلُّوهُمُ","text_uthmani":"تُوَلُّوهُمُ","line_number":13,"text_uthmani_tajweed":"تُوَلُّوهُمُ","page_number":178,"text":"تُوَلُّوهُمُ","translation":{"text":"turn to them","language_name":"english"},"transliteration":{"text":"tuwallūhumu","language_name":"english"}},{"id":17259,"position":11,"audio_url":"wbw/008_015_011.mp3","char_type_name":"word","text_qpc_hafs":"ٱلۡأَدۡبَارَ","text_uthmani":"ٱلْأَدْبَارَ","line_number":13,"text_uthmani_tajweed":"<rule class=ham_wasl>ٱ</rule>لۡأَ<rule class=qalaqah>دۡ</rule>ب<rule class=madda_permissible>َا</rule>رَ","page_number":178,"text":"ٱلْأَدْبَارَ","translation":{"text":"the backs","language_name":"english"},"transliteration":{"text":"l-adbāra","language_name":"english"}},{"id":17260,"position":12,"audio_url":null,"char_type_name":"end","text_qpc_hafs":"١٥","text_uthmani":"١٥","line_number":13,"text_uthmani_tajweed":"١٥","page_number":178,"text":"١٥","translation":{"text":"(15)","language_name":"english"},"transliteration":{"text":null,"language_name":"english"}}],"audio":{"url":"Alafasy/mp3/008015.mp3","segments":[[0,1,70,2920],[1,2,2930,4080],[2,3,4090,6420],[3,4,6430,7030],[4,5,7040,8150],[5,6,8160,9270],[6,7,9280,10210],[7,8,10220,11750],[8,9,11760,12420],[9,10,12430,14070],[10,11,14080,15080]]},"translations":[{"id":402878,"resource_id":85,"text":"Believers, when you meet the disbelievers in battle, never turn your backs on them:"}]},{"id":1176,"verse_number":16,"verse_key":"8:16","hizb_number":18,"rub_el_hizb_number":71,"ruku_number":147,"manzil_number":2,"sajdah_number":null,"text_qpc_hafs":"وَمَن يُوَلِّهِمۡ يَوۡمَئِذٖ دُبُرَهُۥٓ إِلَّا مُتَحَرِّفٗا لِّقِتَالٍ أَوۡ مُتَحَيِّزًا إِلَىٰ فِئَةٖ فَقَدۡ بَآءَ بِغَضَبٖ مِّنَ ٱللَّهِ وَمَأۡوَىٰهُ جَهَنَّمُۖ وَبِئۡسَ ٱلۡمَصِيرُ ١٦","text_uthmani":"وَمَن يُوَلِّهِمْ يَوْمَئِذٍ دُبُرَهُۥٓ إِلَّا مُتَحَرِّفًا لِّقِتَالٍ أَوْ مُتَحَيِّزًا إِلَىٰ فِئَةٍ فَقَدْ بَآءَ بِغَضَبٍ مِّنَ ٱللَّهِ وَمَأْوَىٰهُ جَهَنَّمُ ۖ وَبِئْسَ ٱلْمَصِيرُ","page_number":178,"juz_number":9,"words":[{"id":18313,"position":1,"audio_url":"wbw/008_016_001.mp3","char_type_name":"word","text_qpc_hafs":"وَمَن","text_uthmani":"وَمَن","line_number":13,"text_uthmani_tajweed":"وَم<rule class=idgham_ghunnah>َن</rule>","page_number":178,"text":"وَمَن","translation":{"text":"And whoever","language_name":"english"},"transliteration":{"text":"waman","language_name":"english"}},{"id":18314,"position":2,"audio_url":"wbw/008_016_002.mp3","char_type_name":"word","text_qpc_hafs":"يُوَلِّهِمۡ","text_uthmani":"يُوَلِّهِمْ","line_number":13,"text_uthmani_tajweed":"<rule class=idgham_ghunnah>ي</rule>ُوَلِّهِمۡ","page_number":178,"text":"يُوَلِّهِمْ","translation":{"text":"turns to them","language_name":"english"},"transliteration":{"text":"yuwallihim","language_name":"english"}},{"id":18315,"position":3,"audio_url":"wbw/008_016_003.mp3","char_type_name":"word","text_qpc_hafs":"يَوۡمَئِذٖ","text_uthmani":"يَوْمَئِذٍۢ","line_number":13,"text_uthmani_tajweed":"يَوۡمَئِ<rule class=ikhafa>ذٍ</rule>","page_number":178,"text":"يَوْمَئِذٍۢ","translation":{"text":"that day","language_name":"english"},"transliteration":{"text":"yawma-idhin","language_name":"english"}},{"id":18316,"position":4,"audio_url":"wbw/008_016_004.mp3","char_type_name":"word","text_qpc_hafs":"دُبُرَهُۥٓ","text_uthmani":"دُبُرَهُۥٓ","line_number":14,"text_uthmani_tajweed":"<rule class=ikhafa>د</rule>ُبُرَهُ<rule class=madda_obligatory_monfasel>ۥٓ</rule>","page_number":178,"text":"دُبُرَهُۥٓ","translation":{"text":"his back","language_name":"english"},"transliteration":{"text":"duburahu","language_name":"english"}},{"id":18317,"position":5,"audio_url":"wbw/008_016_005.mp3","char_type_name":"word","text_qpc_hafs":"إِلَّا","text_uthmani":"إِلَّا","line_number":14,"text_uthmani_tajweed":"إِلَّا","page_number":178,"text":"إِلَّا","translation":{"text":"except","language_name":"english"},"transliteration":{"text":"illā","language_name":"english"}},{"id":18318,"position":6,"audio_url":"wbw/008_016_006.mp3","char_type_name":"word","text_qpc_hafs":"مُتَحَرِّفٗا","text_uthmani":"مُتَحَرِّفًۭا","line_number":14,"text_uthmani_tajweed":"مُتَحَرِّ<rule class=idgham_wo_ghunnah>فًا</rule>","page_number":178,"text":"مُتَحَرِّفًۭا","translation":{"text":"(as) a strategy","language_name":"english"},"transliteration":{"text":"mutaḥarrifan","language_name":"english"}},{"id":18319,"position":7,"audio_url":"wbw/008_016_007.mp3","char_type_name":"word","text_qpc_hafs":"لِّقِتَالٍ","text_uthmani":"لِّقِتَالٍ","line_number":14,"text_uthmani_tajweed":"<rule class=idgham_wo_ghunnah>ل</rule>ِّقِتَالٍ","page_number":178,"text":"لِّقِتَالٍ","translation":{"text":"of war","language_name":"english"},"transliteration":{"text":"liqitālin","language_name":"english"}},{"id":18320,"position":8,"audio_url":"wbw/008_016_008.mp3","char_type_name":"word","text_qpc_hafs":"أَوۡ","text_uthmani":"أَوْ","line_number":14,"text_uthmani_tajweed":"أَوۡ","page_number":178,"text":"أَوْ","translation":{"text":"or","language_name":"english"},"transliteration":{"text":"aw","language_name":"english"}},{"id":18321,"position":9,"audio_url":"wbw/008_016_009.mp3","char_type_name":"word","text_qpc_hafs":"مُتَحَيِّزًا","text_uthmani":"مُتَحَيِّزًا","line_number":14,"text_uthmani_tajweed":"مُتَحَيِّزًا","page_number":178,"text":"مُتَحَيِّزًا","translation":{"text":"(to) join","language_name":"english"},"transliteration":{"text":"mutaḥayyizan","language_name":"english"}},{"id":18322,"position":10,"audio_url":"wbw/008_016_010.mp3","char_type_name":"word","text_qpc_hafs":"إِلَىٰ","text_uthmani":"إِلَىٰ","line_number":14,"text_uthmani_tajweed":"إِلَىٰ","page_number":178,"text":"إِلَىٰ","translation":{"text":"to","language_name":"english"},"transliteration":{"text":"ilā","language_name":"english"}},{"id":18323,"position":11,"audio_url":"wbw/008_016_011.mp3","char_type_name":"word","text_qpc_hafs":"فِئَةٖ","text_uthmani":"فِئَةٍۢ","line_number":14,"text_uthmani_tajweed":"فِئَ<rule class=ikhafa>ةٍ</rule>","page_number":178,"text":"فِئَةٍۢ","translation":{"text":"a group","language_name":"english"},"transliteration":{"text":"fi-atin","language_name":"english"}},{"id":18324,"position":12,"audio_url":"wbw/008_016_012.mp3","char_type_name":"word","text_qpc_hafs":"فَقَدۡ","text_uthmani":"فَقَدْ","line_number":14,"text_uthmani_tajweed":"<rule class=ikhafa>ف</rule>َقَ<rule class=qalaqah>دۡ</rule>","page_number":178,"text":"فَقَدْ","translation":{"text":"certainly","language_name":"english"},"transliteration":{"text":"faqad","language_name":"english"}},{"id":18325,"position":13,"audio_url":"wbw/008_016_013.mp3","char_type_name":"word","text_qpc_hafs":"بَآءَ","text_uthmani":"بَآءَ","line_number":14,"text_uthmani_tajweed":"ب<rule class=madda_obligatory_mottasel>َا</rule>ٓءَ","page_number":178,"text":"بَآءَ","translation":{"text":"(he has) incurred","language_name":"english"},"transliteration":{"text":"bāa","language_name":"english"}},{"id":18326,"position":14,"audio_url":"wbw/008_016_014.mp3","char_type_name":"word","text_qpc_hafs":"بِغَضَبٖ","text_uthmani":"بِغَضَبٍۢ","line_number":15,"text_uthmani_tajweed":"بِغَضَ<rule class=idgham_ghunnah>بٍ</rule>","page_number":178,"text":"بِغَضَبٍۢ","translation":{"text":"wrath","language_name":"english"},"transliteration":{"text":"bighaḍabin","language_name":"english"}},{"id":18327,"position":15,"audio_url":"wbw/008_016_015.mp3","char_type_name":"word","text_qpc_hafs":"مِّنَ","text_uthmani":"مِّنَ","line_number":15,"text_uthmani_tajweed":"<rule class=idgham_ghunnah>م</rule>ِّنَ","page_number":178,"text":"مِّنَ","translation":{"text":"of","language_name":"english"},"transliteration":{"text":"mina","language_name":"english"}},{"id":18328,"position":16,"audio_url":"wbw/008_016_016.mp3","char_type_name":"word","text_qpc_hafs":"ٱللَّهِ","text_uthmani":"ٱللَّهِ","line_number":15,"text_uthmani_tajweed":"<rule class=ham_wasl>ٱ</rule>للَّهِ","page_number":178,"text":"ٱللَّهِ","translation":{"text":"Allah","language_name":"english"},"transliteration":{"text":"l-lahi","language_name":"english"}},{"id":18329,"position":17,"audio_url":"wbw/008_016_017.mp3","char_type_name":"word","text_qpc_hafs":"وَمَأۡوَىٰهُ","text_uthmani":"وَمَأْوَىٰهُ","line_number":15,"text_uthmani_tajweed":"وَمَأۡوَ<rule class=madda_normal>ٮٰ</rule>هُ","page_number":178,"text":"وَمَأْوَىٰهُ","translation":{"text":"and his abode","language_name":"english"},"transliteration":{"text":"wamawāhu","language_name":"english"}},{"id":18330,"position":18,"audio_url":"wbw/008_016_018.mp3","char_type_name":"word","text_qpc_hafs":"جَهَنَّمُۖ","text_uthmani":"جَهَنَّمُ ۖ","line_number":15,"text_uthmani_tajweed":"جَهَ<rule class=ghunnah>نّ</rule>َمُ‌ۖ","page_number":178,"text":"جَهَنَّمُ ۖ","translation":{"text":"(is) Hell","language_name":"english"},"transliteration":{"text":"jahannamu","language_name":"english"}},{"id":18332,"position":19,"audio_url":"wbw/008_016_020.mp3","char_type_name":"word","text_qpc_hafs":"وَبِئۡسَ","text_uthmani":"وَبِئْسَ","line_number":15,"text_uthmani_tajweed":"وَبِئۡسَ","page_number":178,"text":"وَبِئْسَ","translation":{"text":"a wretched","language_name":"english"},"transliteration":{"text":"wabi'sa","language_name":"english"}},{"id":18333,"position":20,"audio_url":"wbw/008_016_021.mp3","char_type_name":"word","text_qpc_hafs":"ٱلۡمَصِيرُ","text_uthmani":"ٱلْمَصِيرُ","line_number":15,"text_uthmani_tajweed":"<rule class=ham_wasl>ٱ</rule>لۡمَص<rule class=madda_permissible>ِي</rule>رُ","page_number":178,"text":"ٱلْمَصِيرُ","translation":{"text":"destination","language_name":"english"},"transliteration":{"text":"l-maṣīru","language_name":"english"}},{"id":18334,"position":21,"audio_url":null,"char_type_name":"end","text_qpc_hafs":"١٦","text_uthmani":"١٦","line_number":15,"text_uthmani_tajweed":"١٦","page_number":178,"text":"١٦","translation":{"text":"(16)","language_name":"english"},"transliteration":{"text":null,"language_name":"english"}}],"audio":{"url":"Alafasy/mp3/008016.mp3","segments":[[0,1,140,1530],[1,2,1540,2750],[2,3,2760,4740],[3,4,4750,7230],[4,5,7240,8090],[5,6,8100,9330],[6,7,9340,11010],[7,8,11020,11440],[8,9,11450,13050],[9,10,13060,13670],[10,11,13680,15270],[11,12,15280,15960],[12,13,15970,21770],[13,14,21780,23460],[14,15,23470,23780],[15,16,23790,24710],[16,17,24720,26060],[17,18,26070,27660],[18,19,27670,28650],[19,20,28660,31090]]},"translations":[{"id":402879,"resource_id":85,"text":"if anyone does so on such a day- unless maneuvring to fight or to join a fighting group- he incurs the wrath of God, and Hell will be his home, a wretched destination!"}]}]