[{"id":2361,"verse_number":13,"verse_key":"20:13","hizb_number":32,"rub_el_hizb_number":125,"ruku_number":270,"manzil_number":4,"sajdah_number":null,"text_qpc_hafs":"وَأَنَا ٱخۡتَرۡتُكَ فَٱسۡتَمِعۡ لِمَا يُوحَىٰٓ ١٣","text_uthmani":"وَأَنَا ٱخْتَرْتُكَ فَٱسْتَمِعْ لِمَا يُوحَىٰٓ","page_number":313,"juz_number":16,"words":[{"id":14938,"position":1,"audio_url":"wbw/020_013_001.mp3","char_type_name":"word","text_qpc_hafs":"وَأَنَا","text_uthmani":"وَأَنَا","line_number":1,"text_uthmani_tajweed":"وَأَنَا","page_number":313,"text":"وَأَنَا","translation":{"text":"And I","language_name":"english"},"transliteration":{"text":"wa-anā","language_name":"english"}},{"id":14939,"position":2,"audio_url":"wbw/020_013_002.mp3","char_type_name":"word","text_qpc_hafs":"ٱخۡتَرۡتُكَ","text_uthmani":"ٱخْتَرْتُكَ","line_number":1,"text_uthmani_tajweed":"<rule class=ham_wasl>ٱ</rule>خۡتَرۡتُكَ","page_number":313,"text":"ٱخْتَرْتُكَ","translation":{"text":"(have) chosen you","language_name":"english"},"transliteration":{"text":"ikh'tartuka","language_name":"english"}},{"id":14940,"position":3,"audio_url":"wbw/020_013_003.mp3","char_type_name":"word","text_qpc_hafs":"فَٱسۡتَمِعۡ","text_uthmani":"فَٱسْتَمِعْ","line_number":1,"text_uthmani_tajweed":"فَ<rule class=ham_wasl>ٱ</rule>سۡتَمِعۡ","page_number":313,"text":"فَٱسْتَمِعْ","translation":{"text":"so listen","language_name":"english"},"transliteration":{"text":"fa-is'tamiʿ","language_name":"english"}},{"id":14941,"position":4,"audio_url":"wbw/020_013_004.mp3","char_type_name":"word","text_qpc_hafs":"لِمَا","text_uthmani":"لِمَا","line_number":1,"text_uthmani_tajweed":"لِمَا","page_number":313,"text":"لِمَا","translation":{"text":"to what","language_name":"english"},"transliteration":{"text":"limā","language_name":"english"}},{"id":14942,"position":5,"audio_url":"wbw/020_013_005.mp3","char_type_name":"word","text_qpc_hafs":"يُوحَىٰٓ","text_uthmani":"يُوحَىٰٓ","line_number":1,"text_uthmani_tajweed":"يُوحَىٰٓ","page_number":313,"text":"يُوحَىٰٓ","translation":{"text":"is revealed","language_name":"english"},"transliteration":{"text":"yūḥā","language_name":"english"}},{"id":14943,"position":6,"audio_url":null,"char_type_name":"end","text_qpc_hafs":"١٣","text_uthmani":"١٣","line_number":1,"text_uthmani_tajweed":"١٣","page_number":313,"text":"١٣","translation":{"text":"(13)","language_name":"english"},"transliteration":{"text":null,"language_name":"english"}}],"audio":{"url":"Alafasy/mp3/020013.mp3","segments":[[0,1,160,710],[1,2,720,1900],[2,3,1910,3100],[3,4,3110,3820],[4,5,3830,5200]]},"translations":[{"id":404064,"resource_id":85,"text":"I have chosen you, so listen to what is being revealed."}]},{"id":2362,"verse_number":14,"verse_key":"20:14","hizb_number":32,"rub_el_hizb_number":125,"ruku_number":270,"manzil_number":4,"sajdah_number":null,"text_qpc_hafs":"إِنَّنِيٓ أَنَا ٱللَّهُ لَآ إِلَٰهَ إِلَّآ أَنَا۠ فَٱعۡبُدۡنِي وَأَقِمِ ٱلصَّلَوٰةَ لِذِكۡرِيٓ ١٤","text_uthmani":"إِنَّنِىٓ أَنَا ٱللَّهُ لَآ إِلَـٰهَ إِلَّآ أَنَا۠ فَٱعْبُدْنِى وَأَقِمِ ٱلصَّلَوٰةَ لِذِكْرِىٓ","page_number":313,"juz_number":16,"words":[{"id":16004,"position":1,"audio_url":"wbw/020_014_001.mp3","char_type_name":"word","text_qpc_hafs":"إِنَّنِيٓ","text_uthmani":"إِنَّنِىٓ","line_number":1,"text_uthmani_tajweed":"إِ<rule class=ghunnah>نّ</rule>َن<rule class=madda_obligatory_monfasel>ِىٓ</rule>","page_number":313,"text":"إِنَّنِىٓ","translation":{"text":"Indeed, [I]","language_name":"english"},"transliteration":{"text":"innanī","language_name":"english"}},{"id":16005,"position":2,"audio_url":"wbw/020_014_002.mp3","char_type_name":"word","text_qpc_hafs":"أَنَا","text_uthmani":"أَنَا","line_number":1,"text_uthmani_tajweed":"أَنَا","page_number":313,"text":"أَنَا","translation":{"text":"I Am","language_name":"english"},"transliteration":{"text":"anā","language_name":"english"}},{"id":16006,"position":3,"audio_url":"wbw/020_014_003.mp3","char_type_name":"word","text_qpc_hafs":"ٱللَّهُ","text_uthmani":"ٱللَّهُ","line_number":1,"text_uthmani_tajweed":"<rule class=ham_wasl>ٱ</rule>للَّهُ","page_number":313,"text":"ٱللَّهُ","translation":{"text":"Allah","language_name":"english"},"transliteration":{"text":"l-lahu","language_name":"english"}},{"id":16007,"position":4,"audio_url":"wbw/020_014_004.mp3","char_type_name":"word","text_qpc_hafs":"لَآ","text_uthmani":"لَآ","line_number":1,"text_uthmani_tajweed":"ل<rule class=madda_obligatory_monfasel>َآ</rule>","page_number":313,"text":"لَآ","translation":{"text":"(There is) no","language_name":"english"},"transliteration":{"text":"lā","language_name":"english"}},{"id":16008,"position":5,"audio_url":"wbw/020_014_005.mp3","char_type_name":"word","text_qpc_hafs":"إِلَٰهَ","text_uthmani":"إِلَـٰهَ","line_number":1,"text_uthmani_tajweed":"إِلَ<rule class=madda_normal>ـٰ</rule>هَ","page_number":313,"text":"إِلَـٰهَ","translation":{"text":"god","language_name":"english"},"transliteration":{"text":"ilāha","language_name":"english"}},{"id":16009,"position":6,"audio_url":"wbw/020_014_006.mp3","char_type_name":"word","text_qpc_hafs":"إِلَّآ","text_uthmani":"إِلَّآ","line_number":1,"text_uthmani_tajweed":"إِلّ<rule class=madda_obligatory_monfasel>َآ</rule>","page_number":313,"text":"إِلَّآ","translation":{"text":"but","language_name":"english"},"transliteration":{"text":"illā","language_name":"english"}},{"id":16010,"position":7,"audio_url":"wbw/020_014_007.mp3","char_type_name":"word","text_qpc_hafs":"أَنَا۠","text_uthmani":"أَنَا۠","line_number":1,"text_uthmani_tajweed":"أَنَاۡ","page_number":313,"text":"أَنَا۠","translation":{"text":"I","language_name":"english"},"transliteration":{"text":"anā","language_name":"english"}},{"id":16011,"position":8,"audio_url":"wbw/020_014_008.mp3","char_type_name":"word","text_qpc_hafs":"فَٱعۡبُدۡنِي","text_uthmani":"فَٱعْبُدْنِى","line_number":2,"text_uthmani_tajweed":"فَ<rule class=ham_wasl>ٱ</rule>عۡبُ<rule class=qalaqah>دۡ</rule>نِى","page_number":313,"text":"فَٱعْبُدْنِى","translation":{"text":"so worship Me","language_name":"english"},"transliteration":{"text":"fa-uʿ'bud'nī","language_name":"english"}},{"id":16012,"position":9,"audio_url":"wbw/020_014_009.mp3","char_type_name":"word","text_qpc_hafs":"وَأَقِمِ","text_uthmani":"وَأَقِمِ","line_number":2,"text_uthmani_tajweed":"وَأَقِمِ","page_number":313,"text":"وَأَقِمِ","translation":{"text":"and establish","language_name":"english"},"transliteration":{"text":"wa-aqimi","language_name":"english"}},{"id":16013,"position":10,"audio_url":"wbw/020_014_010.mp3","char_type_name":"word","text_qpc_hafs":"ٱلصَّلَوٰةَ","text_uthmani":"ٱلصَّلَوٰةَ","line_number":2,"text_uthmani_tajweed":"<rule class=ham_wasl>ٱ</rule><rule class=laam_shamsiyah>ل</rule>صَّلَ<rule class=slnt>و</rule><rule class=madda_normal>ٰ</rule>ةَ","page_number":313,"text":"ٱلصَّلَوٰةَ","translation":{"text":"the prayer","language_name":"english"},"transliteration":{"text":"l-ṣalata","language_name":"english"}},{"id":16014,"position":11,"audio_url":"wbw/020_014_011.mp3","char_type_name":"word","text_qpc_hafs":"لِذِكۡرِيٓ","text_uthmani":"لِذِكْرِىٓ","line_number":2,"text_uthmani_tajweed":"لِذِكۡرِىٓ","page_number":313,"text":"لِذِكْرِىٓ","translation":{"text":"for My remembrance","language_name":"english"},"transliteration":{"text":"lidhik'rī","language_name":"english"}},{"id":16015,"position":12,"audio_url":null,"char_type_name":"end","text_qpc_hafs":"١٤","text_uthmani":"١٤","line_number":2,"text_uthmani_tajweed":"١٤","page_number":313,"text":"١٤","translation":{"text":"(14)","language_name":"english"},"transliteration":{"text":null,"language_name":"english"}}],"audio":{"url":"Alafasy/mp3/020014.mp3","segments":[[0,1,30,3280],[1,2,3290,3690],[2,3,3700,4660],[3,4,4670,4730],[4,5,4740,7810],[5,6,7820,9200],[6,7,9210,10690],[7,8,10700,12130],[8,9,12140,12950],[9,10,12960,14160],[10,11,14170,15350]]},"translations":[{"id":404065,"resource_id":85,"text":"I am God; there is no god but Me. So worship Me and keep up the prayer so that you remember Me."}]},{"id":2363,"verse_number":15,"verse_key":"20:15","hizb_number":32,"rub_el_hizb_number":125,"ruku_number":270,"manzil_number":4,"sajdah_number":null,"text_qpc_hafs":"إِنَّ ٱلسَّاعَةَ ءَاتِيَةٌ أَكَادُ أُخۡفِيهَا لِتُجۡزَىٰ كُلُّ نَفۡسِۭ بِمَا تَسۡعَىٰ ١٥","text_uthmani":"إِنَّ ٱلسَّاعَةَ ءَاتِيَةٌ أَكَادُ أُخْفِيهَا لِتُجْزَىٰ كُلُّ نَفْسٍۭ بِمَا تَسْعَىٰ","page_number":313,"juz_number":16,"words":[{"id":17234,"position":1,"audio_url":"wbw/020_015_001.mp3","char_type_name":"word","text_qpc_hafs":"إِنَّ","text_uthmani":"إِنَّ","line_number":2,"text_uthmani_tajweed":"إِ<rule class=ghunnah>نّ</rule>َ","page_number":313,"text":"إِنَّ","translation":{"text":"Indeed","language_name":"english"},"transliteration":{"text":"inna","language_name":"english"}},{"id":17235,"position":2,"audio_url":"wbw/020_015_002.mp3","char_type_name":"word","text_qpc_hafs":"ٱلسَّاعَةَ","text_uthmani":"ٱلسَّاعَةَ","line_number":2,"text_uthmani_tajweed":"<rule class=ham_wasl>ٱ</rule><rule class=laam_shamsiyah>ل</rule>سَّاعَةَ","page_number":313,"text":"ٱلسَّاعَةَ","translation":{"text":"the Hour","language_name":"english"},"transliteration":{"text":"l-sāʿata","language_name":"english"}},{"id":17236,"position":3,"audio_url":"wbw/020_015_003.mp3","char_type_name":"word","text_qpc_hafs":"ءَاتِيَةٌ","text_uthmani":"ءَاتِيَةٌ","line_number":2,"text_uthmani_tajweed":"ءَاتِيَةٌ","page_number":313,"text":"ءَاتِيَةٌ","translation":{"text":"(will be) coming","language_name":"english"},"transliteration":{"text":"ātiyatun","language_name":"english"}},{"id":17237,"position":4,"audio_url":"wbw/020_015_004.mp3","char_type_name":"word","text_qpc_hafs":"أَكَادُ","text_uthmani":"أَكَادُ","line_number":3,"text_uthmani_tajweed":"أَكَادُ","page_number":313,"text":"أَكَادُ","translation":{"text":"I almost","language_name":"english"},"transliteration":{"text":"akādu","language_name":"english"}},{"id":17238,"position":5,"audio_url":"wbw/020_015_005.mp3","char_type_name":"word","text_qpc_hafs":"أُخۡفِيهَا","text_uthmani":"أُخْفِيهَا","line_number":3,"text_uthmani_tajweed":"أُخۡفِيهَا","page_number":313,"text":"أُخْفِيهَا","translation":{"text":"[I] hide it","language_name":"english"},"transliteration":{"text":"ukh'fīhā","language_name":"english"}},{"id":17239,"position":6,"audio_url":"wbw/020_015_006.mp3","char_type_name":"word","text_qpc_hafs":"لِتُجۡزَىٰ","text_uthmani":"لِتُجْزَىٰ","line_number":3,"text_uthmani_tajweed":"لِتُ<rule class=qalaqah>جۡ</rule>زَىٰ","page_number":313,"text":"لِتُجْزَىٰ","translation":{"text":"that may be recompensed","language_name":"english"},"transliteration":{"text":"lituj'zā","language_name":"english"}},{"id":17240,"position":7,"audio_url":"wbw/020_015_007.mp3","char_type_name":"word","text_qpc_hafs":"كُلُّ","text_uthmani":"كُلُّ","line_number":3,"text_uthmani_tajweed":"كُلُّ","page_number":313,"text":"كُلُّ","translation":{"text":"every","language_name":"english"},"transliteration":{"text":"kullu","language_name":"english"}},{"id":17241,"position":8,"audio_url":"wbw/020_015_008.mp3","char_type_name":"word","text_qpc_hafs":"نَفۡسِۭ","text_uthmani":"نَفْسٍۭ","line_number":3,"text_uthmani_tajweed":"نَفۡ<rule class=iqlab>سِۭ</rule>","page_number":313,"text":"نَفْسٍۭ","translation":{"text":"soul","language_name":"english"},"transliteration":{"text":"nafsin","language_name":"english"}},{"id":17242,"position":9,"audio_url":"wbw/020_015_009.mp3","char_type_name":"word","text_qpc_hafs":"بِمَا","text_uthmani":"بِمَا","line_number":3,"text_uthmani_tajweed":"<rule class=iqlab>ب</rule>ِمَا","page_number":313,"text":"بِمَا","translation":{"text":"for what","language_name":"english"},"transliteration":{"text":"bimā","language_name":"english"}},{"id":17243,"position":10,"audio_url":"wbw/020_015_010.mp3","char_type_name":"word","text_qpc_hafs":"تَسۡعَىٰ","text_uthmani":"تَسْعَىٰ","line_number":3,"text_uthmani_tajweed":"تَسۡعَىٰ","page_number":313,"text":"تَسْعَىٰ","translation":{"text":"it strives","language_name":"english"},"transliteration":{"text":"tasʿā","language_name":"english"}},{"id":17244,"position":11,"audio_url":null,"char_type_name":"end","text_qpc_hafs":"١٥","text_uthmani":"١٥","line_number":3,"text_uthmani_tajweed":"١٥","page_number":313,"text":"١٥","translation":{"text":"(15)","language_name":"english"},"transliteration":{"text":null,"language_name":"english"}}],"audio":{"url":"Alafasy/mp3/020015.mp3","segments":[[0,1,90,1250],[1,2,1260,2460],[2,3,2470,3790],[3,4,3800,4770],[4,5,4780,6120],[5,6,6130,7230],[6,7,7240,7980],[7,8,7990,9450],[8,9,9460,10150],[9,10,10160,11410]]},"translations":[{"id":404066,"resource_id":85,"text":"The Hour is coming––though I choose to keep it hidden––for each soul to be rewarded for its labour."}]},{"id":2364,"verse_number":16,"verse_key":"20:16","hizb_number":32,"rub_el_hizb_number":125,"ruku_number":270,"manzil_number":4,"sajdah_number":null,"text_qpc_hafs":"فَلَا يَصُدَّنَّكَ عَنۡهَا مَن لَّا يُؤۡمِنُ بِهَا وَٱتَّبَعَ هَوَىٰهُ فَتَرۡدَىٰ ١٦","text_uthmani":"فَلَا يَصُدَّنَّكَ عَنْهَا مَن لَّا يُؤْمِنُ بِهَا وَٱتَّبَعَ هَوَىٰهُ فَتَرْدَىٰ","page_number":313,"juz_number":16,"words":[{"id":18281,"position":1,"audio_url":"wbw/020_016_001.mp3","char_type_name":"word","text_qpc_hafs":"فَلَا","text_uthmani":"فَلَا","line_number":3,"text_uthmani_tajweed":"فَلَا","page_number":313,"text":"فَلَا","translation":{"text":"So (do) not","language_name":"english"},"transliteration":{"text":"falā","language_name":"english"}},{"id":18282,"position":2,"audio_url":"wbw/020_016_002.mp3","char_type_name":"word","text_qpc_hafs":"يَصُدَّنَّكَ","text_uthmani":"يَصُدَّنَّكَ","line_number":3,"text_uthmani_tajweed":"يَصُدَّ<rule class=ghunnah>نّ</rule>َكَ","page_number":313,"text":"يَصُدَّنَّكَ","translation":{"text":"(let) avert you","language_name":"english"},"transliteration":{"text":"yaṣuddannaka","language_name":"english"}},{"id":18283,"position":3,"audio_url":"wbw/020_016_003.mp3","char_type_name":"word","text_qpc_hafs":"عَنۡهَا","text_uthmani":"عَنْهَا","line_number":4,"text_uthmani_tajweed":"عَنۡهَا","page_number":313,"text":"عَنْهَا","translation":{"text":"from it","language_name":"english"},"transliteration":{"text":"ʿanhā","language_name":"english"}},{"id":18284,"position":4,"audio_url":"wbw/020_016_004.mp3","char_type_name":"word","text_qpc_hafs":"مَن","text_uthmani":"مَن","line_number":4,"text_uthmani_tajweed":"م<rule class=idgham_wo_ghunnah>َن</rule>","page_number":313,"text":"مَن","translation":{"text":"(one) who","language_name":"english"},"transliteration":{"text":"man","language_name":"english"}},{"id":18285,"position":5,"audio_url":"wbw/020_016_005.mp3","char_type_name":"word","text_qpc_hafs":"لَّا","text_uthmani":"لَّا","line_number":4,"text_uthmani_tajweed":"<rule class=idgham_wo_ghunnah>ل</rule>َّا","page_number":313,"text":"لَّا","translation":{"text":"(does) not","language_name":"english"},"transliteration":{"text":"lā","language_name":"english"}},{"id":18286,"position":6,"audio_url":"wbw/020_016_006.mp3","char_type_name":"word","text_qpc_hafs":"يُؤۡمِنُ","text_uthmani":"يُؤْمِنُ","line_number":4,"text_uthmani_tajweed":"يُؤۡمِنُ","page_number":313,"text":"يُؤْمِنُ","translation":{"text":"believe","language_name":"english"},"transliteration":{"text":"yu'minu","language_name":"english"}},{"id":18287,"position":7,"audio_url":"wbw/020_016_007.mp3","char_type_name":"word","text_qpc_hafs":"بِهَا","text_uthmani":"بِهَا","line_number":4,"text_uthmani_tajweed":"بِهَا","page_number":313,"text":"بِهَا","translation":{"text":"in it","language_name":"english"},"transliteration":{"text":"bihā","language_name":"english"}},{"id":18288,"position":8,"audio_url":"wbw/020_016_008.mp3","char_type_name":"word","text_qpc_hafs":"وَٱتَّبَعَ","text_uthmani":"وَٱتَّبَعَ","line_number":4,"text_uthmani_tajweed":"وَ<rule class=ham_wasl>ٱ</rule>تَّبَعَ","page_number":313,"text":"وَٱتَّبَعَ","translation":{"text":"and follows","language_name":"english"},"transliteration":{"text":"wa-ittabaʿa","language_name":"english"}},{"id":18289,"position":9,"audio_url":"wbw/020_016_009.mp3","char_type_name":"word","text_qpc_hafs":"هَوَىٰهُ","text_uthmani":"هَوَىٰهُ","line_number":4,"text_uthmani_tajweed":"هَوَ<rule class=madda_normal>ٮٰ</rule>هُ","page_number":313,"text":"هَوَىٰهُ","translation":{"text":"his desires","language_name":"english"},"transliteration":{"text":"hawāhu","language_name":"english"}},{"id":18290,"position":10,"audio_url":"wbw/020_016_010.mp3","char_type_name":"word","text_qpc_hafs":"فَتَرۡدَىٰ","text_uthmani":"فَتَرْدَىٰ","line_number":4,"text_uthmani_tajweed":"فَتَرۡدَىٰ","page_number":313,"text":"فَتَرْدَىٰ","translation":{"text":"lest you perish","language_name":"english"},"transliteration":{"text":"fatardā","language_name":"english"}},{"id":18291,"position":11,"audio_url":null,"char_type_name":"end","text_qpc_hafs":"١٦","text_uthmani":"١٦","line_number":4,"text_uthmani_tajweed":"١٦","page_number":313,"text":"١٦","translation":{"text":"(16)","language_name":"english"},"transliteration":{"text":null,"language_name":"english"}}],"audio":{"url":"Alafasy/mp3/020016.mp3","segments":[[0,1,30,650],[1,2,660,2990],[2,3,3000,3950],[3,4,3960,4150],[4,5,4160,4880],[5,6,4890,5770],[6,7,5780,6510],[7,8,6520,7640],[8,9,7650,8590],[9,10,8600,10110]]},"translations":[{"id":404067,"resource_id":85,"text":"Do not let anyone who does not believe in it and follows his own desires distract you from it, and so bring you to ruin.’"}]},{"id":2365,"verse_number":17,"verse_key":"20:17","hizb_number":32,"rub_el_hizb_number":125,"ruku_number":270,"manzil_number":4,"sajdah_number":null,"text_qpc_hafs":"وَمَا تِلۡكَ بِيَمِينِكَ يَٰمُوسَىٰ ١٧","text_uthmani":"وَمَا تِلْكَ بِيَمِينِكَ يَـٰمُوسَىٰ","page_number":313,"juz_number":16,"words":[{"id":19305,"position":1,"audio_url":"wbw/020_017_001.mp3","char_type_name":"word","text_qpc_hafs":"وَمَا","text_uthmani":"وَمَا","line_number":4,"text_uthmani_tajweed":"وَمَا","page_number":313,"text":"وَمَا","translation":{"text":"And what","language_name":"english"},"transliteration":{"text":"wamā","language_name":"english"}},{"id":19306,"position":2,"audio_url":"wbw/020_017_002.mp3","char_type_name":"word","text_qpc_hafs":"تِلۡكَ","text_uthmani":"تِلْكَ","line_number":4,"text_uthmani_tajweed":"تِلۡكَ","page_number":313,"text":"تِلْكَ","translation":{"text":"(is) that","language_name":"english"},"transliteration":{"text":"til'ka","language_name":"english"}},{"id":19307,"position":3,"audio_url":"wbw/020_017_003.mp3","char_type_name":"word","text_qpc_hafs":"بِيَمِينِكَ","text_uthmani":"بِيَمِينِكَ","line_number":5,"text_uthmani_tajweed":"بِيَمِينِكَ","page_number":313,"text":"بِيَمِينِكَ","translation":{"text":"in your right hand","language_name":"english"},"transliteration":{"text":"biyamīnika","language_name":"english"}},{"id":19308,"position":4,"audio_url":"wbw/020_017_004.mp3","char_type_name":"word","text_qpc_hafs":"يَٰمُوسَىٰ","text_uthmani":"يَـٰمُوسَىٰ","line_number":5,"text_uthmani_tajweed":"يَ<rule class=madda_normal>ـٰ</rule>مُوسَىٰ","page_number":313,"text":"يَـٰمُوسَىٰ","translation":{"text":"O Musa","language_name":"english"},"transliteration":{"text":"yāmūsā","language_name":"english"}},{"id":19309,"position":5,"audio_url":null,"char_type_name":"end","text_qpc_hafs":"١٧","text_uthmani":"١٧","line_number":5,"text_uthmani_tajweed":"١٧","page_number":313,"text":"١٧","translation":{"text":"(17)","language_name":"english"},"transliteration":{"text":null,"language_name":"english"}}],"audio":{"url":"Alafasy/mp3/020017.mp3","segments":[[0,1,30,590],[1,2,600,1310],[2,3,1320,2740],[3,4,2750,4450]]},"translations":[{"id":404068,"resource_id":85,"text":"‘Moses, what is that in your right hand?’"}]},{"id":2366,"verse_number":18,"verse_key":"20:18","hizb_number":32,"rub_el_hizb_number":125,"ruku_number":270,"manzil_number":4,"sajdah_number":null,"text_qpc_hafs":"قَالَ هِيَ عَصَايَ أَتَوَكَّؤُاْ عَلَيۡهَا وَأَهُشُّ بِهَا عَلَىٰ غَنَمِي وَلِيَ فِيهَا مَـَٔارِبُ أُخۡرَىٰ ١٨","text_uthmani":"قَالَ هِىَ عَصَاىَ أَتَوَكَّؤُا۟ عَلَيْهَا وَأَهُشُّ بِهَا عَلَىٰ غَنَمِى وَلِىَ فِيهَا مَـَٔارِبُ أُخْرَىٰ","page_number":313,"juz_number":16,"words":[{"id":20375,"position":1,"audio_url":"wbw/020_018_001.mp3","char_type_name":"word","text_qpc_hafs":"قَالَ","text_uthmani":"قَالَ","line_number":5,"text_uthmani_tajweed":"قَالَ","page_number":313,"text":"قَالَ","translation":{"text":"He said","language_name":"english"},"transliteration":{"text":"qāla","language_name":"english"}},{"id":20376,"position":2,"audio_url":"wbw/020_018_002.mp3","char_type_name":"word","text_qpc_hafs":"هِيَ","text_uthmani":"هِىَ","line_number":5,"text_uthmani_tajweed":"هِىَ","page_number":313,"text":"هِىَ","translation":{"text":"It","language_name":"english"},"transliteration":{"text":"hiya","language_name":"english"}},{"id":20377,"position":3,"audio_url":"wbw/020_018_003.mp3","char_type_name":"word","text_qpc_hafs":"عَصَايَ","text_uthmani":"عَصَاىَ","line_number":5,"text_uthmani_tajweed":"عَصَاىَ","page_number":313,"text":"عَصَاىَ","translation":{"text":"(is) my staff","language_name":"english"},"transliteration":{"text":"ʿaṣāya","language_name":"english"}},{"id":20378,"position":4,"audio_url":"wbw/020_018_004.mp3","char_type_name":"word","text_qpc_hafs":"أَتَوَكَّؤُاْ","text_uthmani":"أَتَوَكَّؤُا۟","line_number":5,"text_uthmani_tajweed":"أَتَوَكَّؤُ<rule class=slnt>اۡ</rule>","page_number":313,"text":"أَتَوَكَّؤُا۟","translation":{"text":"I lean","language_name":"english"},"transliteration":{"text":"atawakka-u","language_name":"english"}},{"id":20379,"position":5,"audio_url":"wbw/020_018_005.mp3","char_type_name":"word","text_qpc_hafs":"عَلَيۡهَا","text_uthmani":"عَلَيْهَا","line_number":5,"text_uthmani_tajweed":"عَلَيۡهَا","page_number":313,"text":"عَلَيْهَا","translation":{"text":"upon it","language_name":"english"},"transliteration":{"text":"ʿalayhā","language_name":"english"}},{"id":20380,"position":6,"audio_url":"wbw/020_018_006.mp3","char_type_name":"word","text_qpc_hafs":"وَأَهُشُّ","text_uthmani":"وَأَهُشُّ","line_number":6,"text_uthmani_tajweed":"وَأَهُشُّ","page_number":313,"text":"وَأَهُشُّ","translation":{"text":"and I bring down leaves","language_name":"english"},"transliteration":{"text":"wa-ahushu","language_name":"english"}},{"id":20381,"position":7,"audio_url":"wbw/020_018_007.mp3","char_type_name":"word","text_qpc_hafs":"بِهَا","text_uthmani":"بِهَا","line_number":6,"text_uthmani_tajweed":"بِهَا","page_number":313,"text":"بِهَا","translation":{"text":"with it","language_name":"english"},"transliteration":{"text":"bihā","language_name":"english"}},{"id":20382,"position":8,"audio_url":"wbw/020_018_008.mp3","char_type_name":"word","text_qpc_hafs":"عَلَىٰ","text_uthmani":"عَلَىٰ","line_number":6,"text_uthmani_tajweed":"عَلَىٰ","page_number":313,"text":"عَلَىٰ","translation":{"text":"for","language_name":"english"},"transliteration":{"text":"ʿalā","language_name":"english"}},{"id":20383,"position":9,"audio_url":"wbw/020_018_009.mp3","char_type_name":"word","text_qpc_hafs":"غَنَمِي","text_uthmani":"غَنَمِى","line_number":6,"text_uthmani_tajweed":"غَنَمِى","page_number":313,"text":"غَنَمِى","translation":{"text":"my sheep","language_name":"english"},"transliteration":{"text":"ghanamī","language_name":"english"}},{"id":20384,"position":10,"audio_url":"wbw/020_018_010.mp3","char_type_name":"word","text_qpc_hafs":"وَلِيَ","text_uthmani":"وَلِىَ","line_number":6,"text_uthmani_tajweed":"وَلِىَ","page_number":313,"text":"وَلِىَ","translation":{"text":"and for me","language_name":"english"},"transliteration":{"text":"waliya","language_name":"english"}},{"id":20385,"position":11,"audio_url":"wbw/020_018_011.mp3","char_type_name":"word","text_qpc_hafs":"فِيهَا","text_uthmani":"فِيهَا","line_number":6,"text_uthmani_tajweed":"فِيهَا","page_number":313,"text":"فِيهَا","translation":{"text":"in it","language_name":"english"},"transliteration":{"text":"fīhā","language_name":"english"}},{"id":20386,"position":12,"audio_url":"wbw/020_018_012.mp3","char_type_name":"word","text_qpc_hafs":"مَـَٔارِبُ","text_uthmani":"مَـَٔارِبُ","line_number":6,"text_uthmani_tajweed":"مَـَٔـارِبُ","page_number":313,"text":"مَـَٔارِبُ","translation":{"text":"(are) uses","language_name":"english"},"transliteration":{"text":"maāribu","language_name":"english"}},{"id":20387,"position":13,"audio_url":"wbw/020_018_013.mp3","char_type_name":"word","text_qpc_hafs":"أُخۡرَىٰ","text_uthmani":"أُخْرَىٰ","line_number":6,"text_uthmani_tajweed":"أُخۡرَىٰ","page_number":313,"text":"أُخْرَىٰ","translation":{"text":"other","language_name":"english"},"transliteration":{"text":"ukh'rā","language_name":"english"}},{"id":20388,"position":14,"audio_url":null,"char_type_name":"end","text_qpc_hafs":"١٨","text_uthmani":"١٨","line_number":6,"text_uthmani_tajweed":"١٨","page_number":313,"text":"١٨","translation":{"text":"(18)","language_name":"english"},"transliteration":{"text":null,"language_name":"english"}}],"audio":{"url":"Alafasy/mp3/020018.mp3","segments":[[0,1,40,720],[1,2,730,1100],[2,3,1110,2130],[3,4,2140,3480],[4,5,3490,4680],[5,6,4690,5840],[6,7,5850,6510],[7,8,6520,7230],[8,9,7240,8280],[9,10,8290,8870],[10,11,8880,9820],[11,12,9830,10960],[12,13,10970,11960]]},"translations":[{"id":404069,"resource_id":85,"text":"‘It is my staff,’ he said, ‘I lean on it; restrain my sheep with it; I also have other uses for it.’"}]},{"id":2367,"verse_number":19,"verse_key":"20:19","hizb_number":32,"rub_el_hizb_number":125,"ruku_number":270,"manzil_number":4,"sajdah_number":null,"text_qpc_hafs":"قَالَ أَلۡقِهَا يَٰمُوسَىٰ ١٩","text_uthmani":"قَالَ أَلْقِهَا يَـٰمُوسَىٰ","page_number":313,"juz_number":16,"words":[{"id":21462,"position":1,"audio_url":"wbw/020_019_001.mp3","char_type_name":"word","text_qpc_hafs":"قَالَ","text_uthmani":"قَالَ","line_number":6,"text_uthmani_tajweed":"قَالَ","page_number":313,"text":"قَالَ","translation":{"text":"He said","language_name":"english"},"transliteration":{"text":"qāla","language_name":"english"}},{"id":21463,"position":2,"audio_url":"wbw/020_019_002.mp3","char_type_name":"word","text_qpc_hafs":"أَلۡقِهَا","text_uthmani":"أَلْقِهَا","line_number":6,"text_uthmani_tajweed":"أَلۡقِهَا","page_number":313,"text":"أَلْقِهَا","translation":{"text":"Throw it down","language_name":"english"},"transliteration":{"text":"alqihā","language_name":"english"}},{"id":21464,"position":3,"audio_url":"wbw/020_019_003.mp3","char_type_name":"word","text_qpc_hafs":"يَٰمُوسَىٰ","text_uthmani":"يَـٰمُوسَىٰ","line_number":7,"text_uthmani_tajweed":"يَ<rule class=madda_normal>ـٰ</rule>مُوسَىٰ","page_number":313,"text":"يَـٰمُوسَىٰ","translation":{"text":"O Musa","language_name":"english"},"transliteration":{"text":"yāmūsā","language_name":"english"}},{"id":21465,"position":4,"audio_url":null,"char_type_name":"end","text_qpc_hafs":"١٩","text_uthmani":"١٩","line_number":7,"text_uthmani_tajweed":"١٩","page_number":313,"text":"١٩","translation":{"text":"(19)","language_name":"english"},"transliteration":{"text":null,"language_name":"english"}}],"audio":{"url":"Alafasy/mp3/020019.mp3","segments":[[0,1,60,670],[1,2,680,1800],[2,3,1810,3500]]},"translations":[{"id":404070,"resource_id":85,"text":"God said, ‘Throw it down, Moses.’"}]},{"id":2368,"verse_number":20,"verse_key":"20:20","hizb_number":32,"rub_el_hizb_number":125,"ruku_number":270,"manzil_number":4,"sajdah_number":null,"text_qpc_hafs":"فَأَلۡقَىٰهَا فَإِذَا هِيَ حَيَّةٞ تَسۡعَىٰ ٢٠","text_uthmani":"فَأَلْقَىٰهَا فَإِذَا هِىَ حَيَّةٌ تَسْعَىٰ","page_number":313,"juz_number":16,"words":[{"id":22548,"position":1,"audio_url":"wbw/020_020_001.mp3","char_type_name":"word","text_qpc_hafs":"فَأَلۡقَىٰهَا","text_uthmani":"فَأَلْقَىٰهَا","line_number":7,"text_uthmani_tajweed":"فَأَلۡقَ<rule class=madda_normal>ـٰ</rule>هَا","page_number":313,"text":"فَأَلْقَىٰهَا","translation":{"text":"So he threw it down","language_name":"english"},"transliteration":{"text":"fa-alqāhā","language_name":"english"}},{"id":22549,"position":2,"audio_url":"wbw/020_020_002.mp3","char_type_name":"word","text_qpc_hafs":"فَإِذَا","text_uthmani":"فَإِذَا","line_number":7,"text_uthmani_tajweed":"فَإِذَا","page_number":313,"text":"فَإِذَا","translation":{"text":"and behold","language_name":"english"},"transliteration":{"text":"fa-idhā","language_name":"english"}},{"id":22550,"position":3,"audio_url":"wbw/020_020_003.mp3","char_type_name":"word","text_qpc_hafs":"هِيَ","text_uthmani":"هِىَ","line_number":7,"text_uthmani_tajweed":"هِىَ","page_number":313,"text":"هِىَ","translation":{"text":"It","language_name":"english"},"transliteration":{"text":"hiya","language_name":"english"}},{"id":22551,"position":4,"audio_url":"wbw/020_020_004.mp3","char_type_name":"word","text_qpc_hafs":"حَيَّةٞ","text_uthmani":"حَيَّةٌۭ","line_number":7,"text_uthmani_tajweed":"حَيَّ<rule class=ikhafa>ةٌ</rule>","page_number":313,"text":"حَيَّةٌۭ","translation":{"text":"(was) a snake","language_name":"english"},"transliteration":{"text":"ḥayyatun","language_name":"english"}},{"id":22552,"position":5,"audio_url":"wbw/020_020_005.mp3","char_type_name":"word","text_qpc_hafs":"تَسۡعَىٰ","text_uthmani":"تَسْعَىٰ","line_number":7,"text_uthmani_tajweed":"<rule class=ikhafa>ت</rule>َسۡعَىٰ","page_number":313,"text":"تَسْعَىٰ","translation":{"text":"moving swiftly","language_name":"english"},"transliteration":{"text":"tasʿā","language_name":"english"}},{"id":22553,"position":6,"audio_url":null,"char_type_name":"end","text_qpc_hafs":"٢٠","text_uthmani":"٢٠","line_number":7,"text_uthmani_tajweed":"٢٠","page_number":313,"text":"٢٠","translation":{"text":"(20)","language_name":"english"},"transliteration":{"text":null,"language_name":"english"}}],"audio":{"url":"Alafasy/mp3/020020.mp3","segments":[[0,1,30,1620],[1,2,1630,2540],[2,3,2550,2980],[3,4,2990,4890],[4,5,4900,6210]]},"translations":[{"id":404071,"resource_id":85,"text":"He threw it down and- lo and behold!- it became a fast-moving snake."}]},{"id":2369,"verse_number":21,"verse_key":"20:21","hizb_number":32,"rub_el_hizb_number":125,"ruku_number":270,"manzil_number":4,"sajdah_number":null,"text_qpc_hafs":"قَالَ خُذۡهَا وَلَا تَخَفۡۖ سَنُعِيدُهَا سِيرَتَهَا ٱلۡأُولَىٰ ٢١","text_uthmani":"قَالَ خُذْهَا وَلَا تَخَفْ ۖ سَنُعِيدُهَا سِيرَتَهَا ٱلْأُولَىٰ","page_number":313,"juz_number":16,"words":[{"id":23711,"position":1,"audio_url":"wbw/020_021_001.mp3","char_type_name":"word","text_qpc_hafs":"قَالَ","text_uthmani":"قَالَ","line_number":7,"text_uthmani_tajweed":"قَالَ","page_number":313,"text":"قَالَ","translation":{"text":"He said","language_name":"english"},"transliteration":{"text":"qāla","language_name":"english"}},{"id":23712,"position":2,"audio_url":"wbw/020_021_002.mp3","char_type_name":"word","text_qpc_hafs":"خُذۡهَا","text_uthmani":"خُذْهَا","line_number":7,"text_uthmani_tajweed":"خُذۡهَا","page_number":313,"text":"خُذْهَا","translation":{"text":"Seize it","language_name":"english"},"transliteration":{"text":"khudh'hā","language_name":"english"}},{"id":23713,"position":3,"audio_url":"wbw/020_021_003.mp3","char_type_name":"word","text_qpc_hafs":"وَلَا","text_uthmani":"وَلَا","line_number":8,"text_uthmani_tajweed":"وَلَا","page_number":313,"text":"وَلَا","translation":{"text":"and (do) not","language_name":"english"},"transliteration":{"text":"walā","language_name":"english"}},{"id":23714,"position":4,"audio_url":"wbw/020_021_004.mp3","char_type_name":"word","text_qpc_hafs":"تَخَفۡۖ","text_uthmani":"تَخَفْ ۖ","line_number":8,"text_uthmani_tajweed":"تَخَفۡ‌ۖ","page_number":313,"text":"تَخَفْ ۖ","translation":{"text":"fear","language_name":"english"},"transliteration":{"text":"takhaf","language_name":"english"}},{"id":23716,"position":5,"audio_url":"wbw/020_021_006.mp3","char_type_name":"word","text_qpc_hafs":"سَنُعِيدُهَا","text_uthmani":"سَنُعِيدُهَا","line_number":8,"text_uthmani_tajweed":"سَنُعِيدُهَا","page_number":313,"text":"سَنُعِيدُهَا","translation":{"text":"We will return it","language_name":"english"},"transliteration":{"text":"sanuʿīduhā","language_name":"english"}},{"id":23717,"position":6,"audio_url":"wbw/020_021_007.mp3","char_type_name":"word","text_qpc_hafs":"سِيرَتَهَا","text_uthmani":"سِيرَتَهَا","line_number":8,"text_uthmani_tajweed":"سِيرَتَهَا","page_number":313,"text":"سِيرَتَهَا","translation":{"text":"(to) its state","language_name":"english"},"transliteration":{"text":"sīratahā","language_name":"english"}},{"id":23718,"position":7,"audio_url":"wbw/020_021_008.mp3","char_type_name":"word","text_qpc_hafs":"ٱلۡأُولَىٰ","text_uthmani":"ٱلْأُولَىٰ","line_number":8,"text_uthmani_tajweed":"<rule class=ham_wasl>ٱ</rule>لۡأُولَىٰ","page_number":313,"text":"ٱلْأُولَىٰ","translation":{"text":"the former","language_name":"english"},"transliteration":{"text":"l-ūlā","language_name":"english"}},{"id":23719,"position":8,"audio_url":null,"char_type_name":"end","text_qpc_hafs":"٢١","text_uthmani":"٢١","line_number":8,"text_uthmani_tajweed":"٢١","page_number":313,"text":"٢١","translation":{"text":"(21)","language_name":"english"},"transliteration":{"text":null,"language_name":"english"}}],"audio":{"url":"Alafasy/mp3/020021.mp3","segments":[[0,1,60,740],[1,2,750,1740],[2,3,1750,2420],[3,4,2430,3500],[4,5,3510,5130],[5,6,5140,6310],[6,7,6320,7560]]},"translations":[{"id":404072,"resource_id":85,"text":"He said, ‘Pick it up without fear: We shall turn it back into its former state."}]},{"id":2370,"verse_number":22,"verse_key":"20:22","hizb_number":32,"rub_el_hizb_number":125,"ruku_number":270,"manzil_number":4,"sajdah_number":null,"text_qpc_hafs":"وَٱضۡمُمۡ يَدَكَ إِلَىٰ جَنَاحِكَ تَخۡرُجۡ بَيۡضَآءَ مِنۡ غَيۡرِ سُوٓءٍ ءَايَةً أُخۡرَىٰ ٢٢","text_uthmani":"وَٱضْمُمْ يَدَكَ إِلَىٰ جَنَاحِكَ تَخْرُجْ بَيْضَآءَ مِنْ غَيْرِ سُوٓءٍ ءَايَةً أُخْرَىٰ","page_number":313,"juz_number":16,"words":[{"id":24670,"position":1,"audio_url":"wbw/020_022_001.mp3","char_type_name":"word","text_qpc_hafs":"وَٱضۡمُمۡ","text_uthmani":"وَٱضْمُمْ","line_number":8,"text_uthmani_tajweed":"وَ<rule class=ham_wasl>ٱ</rule>ضۡمُمۡ","page_number":313,"text":"وَٱضْمُمْ","translation":{"text":"And draw near","language_name":"english"},"transliteration":{"text":"wa-uḍ'mum","language_name":"english"}},{"id":24671,"position":2,"audio_url":"wbw/020_022_002.mp3","char_type_name":"word","text_qpc_hafs":"يَدَكَ","text_uthmani":"يَدَكَ","line_number":8,"text_uthmani_tajweed":"يَدَكَ","page_number":313,"text":"يَدَكَ","translation":{"text":"your hand","language_name":"english"},"transliteration":{"text":"yadaka","language_name":"english"}},{"id":24672,"position":3,"audio_url":"wbw/020_022_003.mp3","char_type_name":"word","text_qpc_hafs":"إِلَىٰ","text_uthmani":"إِلَىٰ","line_number":9,"text_uthmani_tajweed":"إِلَىٰ","page_number":313,"text":"إِلَىٰ","translation":{"text":"to","language_name":"english"},"transliteration":{"text":"ilā","language_name":"english"}},{"id":24673,"position":4,"audio_url":"wbw/020_022_004.mp3","char_type_name":"word","text_qpc_hafs":"جَنَاحِكَ","text_uthmani":"جَنَاحِكَ","line_number":9,"text_uthmani_tajweed":"جَنَاحِكَ","page_number":313,"text":"جَنَاحِكَ","translation":{"text":"your side","language_name":"english"},"transliteration":{"text":"janāḥika","language_name":"english"}},{"id":24674,"position":5,"audio_url":"wbw/020_022_005.mp3","char_type_name":"word","text_qpc_hafs":"تَخۡرُجۡ","text_uthmani":"تَخْرُجْ","line_number":9,"text_uthmani_tajweed":"تَخۡرُ<rule class=qalaqah>جۡ</rule>","page_number":313,"text":"تَخْرُجْ","translation":{"text":"it will come out","language_name":"english"},"transliteration":{"text":"takhruj","language_name":"english"}},{"id":24675,"position":6,"audio_url":"wbw/020_022_006.mp3","char_type_name":"word","text_qpc_hafs":"بَيۡضَآءَ","text_uthmani":"بَيْضَآءَ","line_number":9,"text_uthmani_tajweed":"بَيۡض<rule class=madda_obligatory_mottasel>َا</rule>ٓءَ","page_number":313,"text":"بَيْضَآءَ","translation":{"text":"white","language_name":"english"},"transliteration":{"text":"bayḍāa","language_name":"english"}},{"id":24676,"position":7,"audio_url":"wbw/020_022_007.mp3","char_type_name":"word","text_qpc_hafs":"مِنۡ","text_uthmani":"مِنْ","line_number":9,"text_uthmani_tajweed":"مِنۡ","page_number":313,"text":"مِنْ","translation":{"text":"without any","language_name":"english"},"transliteration":{"text":"min","language_name":"english"}},{"id":24677,"position":8,"audio_url":"wbw/020_022_008.mp3","char_type_name":"word","text_qpc_hafs":"غَيۡرِ","text_uthmani":"غَيْرِ","line_number":9,"text_uthmani_tajweed":"غَيۡرِ","page_number":313,"text":"غَيْرِ","translation":{"text":"without any","language_name":"english"},"transliteration":{"text":"ghayri","language_name":"english"}},{"id":24678,"position":9,"audio_url":"wbw/020_022_009.mp3","char_type_name":"word","text_qpc_hafs":"سُوٓءٍ","text_uthmani":"سُوٓءٍ","line_number":9,"text_uthmani_tajweed":"س<rule class=madda_obligatory_mottasel>ُو</rule>ٓءٍ","page_number":313,"text":"سُوٓءٍ","translation":{"text":"disease","language_name":"english"},"transliteration":{"text":"sūin","language_name":"english"}},{"id":24679,"position":10,"audio_url":"wbw/020_022_010.mp3","char_type_name":"word","text_qpc_hafs":"ءَايَةً","text_uthmani":"ءَايَةً","line_number":9,"text_uthmani_tajweed":"ءَايَةً","page_number":313,"text":"ءَايَةً","translation":{"text":"(as) a sign","language_name":"english"},"transliteration":{"text":"āyatan","language_name":"english"}},{"id":24680,"position":11,"audio_url":"wbw/020_022_011.mp3","char_type_name":"word","text_qpc_hafs":"أُخۡرَىٰ","text_uthmani":"أُخْرَىٰ","line_number":9,"text_uthmani_tajweed":"أُخۡرَىٰ","page_number":313,"text":"أُخْرَىٰ","translation":{"text":"another","language_name":"english"},"transliteration":{"text":"ukh'rā","language_name":"english"}},{"id":24681,"position":12,"audio_url":null,"char_type_name":"end","text_qpc_hafs":"٢٢","text_uthmani":"٢٢","line_number":9,"text_uthmani_tajweed":"٢٢","page_number":313,"text":"٢٢","translation":{"text":"(22)","language_name":"english"},"transliteration":{"text":null,"language_name":"english"}}],"audio":{"url":"Alafasy/mp3/020022.mp3","segments":[[0,1,40,1000],[1,2,1010,1710],[2,3,1720,2370],[3,4,2380,3530],[4,5,3540,4460],[5,6,4470,7380],[6,7,7390,7640],[7,8,7650,8290],[8,9,8300,10640],[9,10,10650,11720],[10,11,11730,12740]]},"translations":[{"id":404073,"resource_id":85,"text":"Now place your hand under your armpit and it will come out white, though unharmed: that is another sign."}]},{"id":2371,"verse_number":23,"verse_key":"20:23","hizb_number":32,"rub_el_hizb_number":125,"ruku_number":270,"manzil_number":4,"sajdah_number":null,"text_qpc_hafs":"لِنُرِيَكَ مِنۡ ءَايَٰتِنَا ٱلۡكُبۡرَى ٢٣","text_uthmani":"لِنُرِيَكَ مِنْ ءَايَـٰتِنَا ٱلْكُبْرَى","page_number":313,"juz_number":16,"words":[{"id":25750,"position":1,"audio_url":"wbw/020_023_001.mp3","char_type_name":"word","text_qpc_hafs":"لِنُرِيَكَ","text_uthmani":"لِنُرِيَكَ","line_number":9,"text_uthmani_tajweed":"لِنُرِيَكَ","page_number":313,"text":"لِنُرِيَكَ","translation":{"text":"That We may show you","language_name":"english"},"transliteration":{"text":"linuriyaka","language_name":"english"}},{"id":25751,"position":2,"audio_url":"wbw/020_023_002.mp3","char_type_name":"word","text_qpc_hafs":"مِنۡ","text_uthmani":"مِنْ","line_number":10,"text_uthmani_tajweed":"مِنۡ","page_number":313,"text":"مِنْ","translation":{"text":"of","language_name":"english"},"transliteration":{"text":"min","language_name":"english"}},{"id":25752,"position":3,"audio_url":"wbw/020_023_003.mp3","char_type_name":"word","text_qpc_hafs":"ءَايَٰتِنَا","text_uthmani":"ءَايَـٰتِنَا","line_number":10,"text_uthmani_tajweed":"ءَايَ<rule class=madda_normal>ـٰ</rule>تِنَا","page_number":313,"text":"ءَايَـٰتِنَا","translation":{"text":"Our Signs","language_name":"english"},"transliteration":{"text":"āyātinā","language_name":"english"}},{"id":25753,"position":4,"audio_url":"wbw/020_023_004.mp3","char_type_name":"word","text_qpc_hafs":"ٱلۡكُبۡرَى","text_uthmani":"ٱلْكُبْرَى","line_number":10,"text_uthmani_tajweed":"<rule class=ham_wasl>ٱ</rule>لۡكُ<rule class=qalaqah>بۡ</rule>رَى","page_number":313,"text":"ٱلْكُبْرَى","translation":{"text":"the Greatest","language_name":"english"},"transliteration":{"text":"l-kub'rā","language_name":"english"}},{"id":25754,"position":5,"audio_url":null,"char_type_name":"end","text_qpc_hafs":"٢٣","text_uthmani":"٢٣","line_number":10,"text_uthmani_tajweed":"٢٣","page_number":313,"text":"٢٣","translation":{"text":"(23)","language_name":"english"},"transliteration":{"text":null,"language_name":"english"}}],"audio":{"url":"Alafasy/mp3/020023.mp3","segments":[[0,1,120,1200],[1,2,1210,1640],[2,3,1650,2960],[3,4,2970,4260]]},"translations":[{"id":404074,"resource_id":85,"text":"We do this to show you some of Our greatest signs."}]},{"id":2372,"verse_number":24,"verse_key":"20:24","hizb_number":32,"rub_el_hizb_number":125,"ruku_number":270,"manzil_number":4,"sajdah_number":null,"text_qpc_hafs":"ٱذۡهَبۡ إِلَىٰ فِرۡعَوۡنَ إِنَّهُۥ طَغَىٰ ٢٤","text_uthmani":"ٱذْهَبْ إِلَىٰ فِرْعَوْنَ إِنَّهُۥ طَغَىٰ","page_number":313,"juz_number":16,"words":[{"id":26820,"position":1,"audio_url":"wbw/020_024_001.mp3","char_type_name":"word","text_qpc_hafs":"ٱذۡهَبۡ","text_uthmani":"ٱذْهَبْ","line_number":10,"text_uthmani_tajweed":"ٱذۡهَ<rule class=qalaqah>بۡ</rule>","page_number":313,"text":"ٱذْهَبْ","translation":{"text":"Go","language_name":"english"},"transliteration":{"text":"idh'hab","language_name":"english"}},{"id":26821,"position":2,"audio_url":"wbw/020_024_002.mp3","char_type_name":"word","text_qpc_hafs":"إِلَىٰ","text_uthmani":"إِلَىٰ","line_number":10,"text_uthmani_tajweed":"إِلَىٰ","page_number":313,"text":"إِلَىٰ","translation":{"text":"to","language_name":"english"},"transliteration":{"text":"ilā","language_name":"english"}},{"id":26822,"position":3,"audio_url":"wbw/020_024_003.mp3","char_type_name":"word","text_qpc_hafs":"فِرۡعَوۡنَ","text_uthmani":"فِرْعَوْنَ","line_number":10,"text_uthmani_tajweed":"فِرۡعَوۡنَ","page_number":313,"text":"فِرْعَوْنَ","translation":{"text":"Firaun","language_name":"english"},"transliteration":{"text":"fir'ʿawna","language_name":"english"}},{"id":26823,"position":4,"audio_url":"wbw/020_024_004.mp3","char_type_name":"word","text_qpc_hafs":"إِنَّهُۥ","text_uthmani":"إِنَّهُۥ","line_number":10,"text_uthmani_tajweed":"إِ<rule class=ghunnah>نّ</rule>َهُ<rule class=madda_normal>ۥ</rule>","page_number":313,"text":"إِنَّهُۥ","translation":{"text":"Indeed, he","language_name":"english"},"transliteration":{"text":"innahu","language_name":"english"}},{"id":26824,"position":5,"audio_url":"wbw/020_024_005.mp3","char_type_name":"word","text_qpc_hafs":"طَغَىٰ","text_uthmani":"طَغَىٰ","line_number":10,"text_uthmani_tajweed":"طَغَىٰ","page_number":313,"text":"طَغَىٰ","translation":{"text":"(has) transgressed","language_name":"english"},"transliteration":{"text":"ṭaghā","language_name":"english"}},{"id":26825,"position":6,"audio_url":null,"char_type_name":"end","text_qpc_hafs":"٢٤","text_uthmani":"٢٤","line_number":10,"text_uthmani_tajweed":"٢٤","page_number":313,"text":"٢٤","translation":{"text":"(24)","language_name":"english"},"transliteration":{"text":null,"language_name":"english"}}],"audio":{"url":"Alafasy/mp3/020024.mp3","segments":[[0,1,30,830],[1,2,840,1490],[2,3,1500,2650],[3,4,2660,4460],[4,5,4470,5460]]},"translations":[{"id":404075,"resource_id":85,"text":"Go to Pharaoh, for he has truly become a tyrant.’"}]},{"id":2373,"verse_number":25,"verse_key":"20:25","hizb_number":32,"rub_el_hizb_number":125,"ruku_number":271,"manzil_number":4,"sajdah_number":null,"text_qpc_hafs":"قَالَ رَبِّ ٱشۡرَحۡ لِي صَدۡرِي ٢٥","text_uthmani":"قَالَ رَبِّ ٱشْرَحْ لِى صَدْرِى","page_number":313,"juz_number":16,"words":[{"id":27909,"position":1,"audio_url":"wbw/020_025_001.mp3","char_type_name":"word","text_qpc_hafs":"قَالَ","text_uthmani":"قَالَ","line_number":10,"text_uthmani_tajweed":"قَالَ","page_number":313,"text":"قَالَ","translation":{"text":"He said","language_name":"english"},"transliteration":{"text":"qāla","language_name":"english"}},{"id":27910,"position":2,"audio_url":"wbw/020_025_002.mp3","char_type_name":"word","text_qpc_hafs":"رَبِّ","text_uthmani":"رَبِّ","line_number":11,"text_uthmani_tajweed":"رَبِّ","page_number":313,"text":"رَبِّ","translation":{"text":"My Lord","language_name":"english"},"transliteration":{"text":"rabbi","language_name":"english"}},{"id":27911,"position":3,"audio_url":"wbw/020_025_003.mp3","char_type_name":"word","text_qpc_hafs":"ٱشۡرَحۡ","text_uthmani":"ٱشْرَحْ","line_number":11,"text_uthmani_tajweed":"<rule class=ham_wasl>ٱ</rule>شۡرَحۡ","page_number":313,"text":"ٱشْرَحْ","translation":{"text":"Expand","language_name":"english"},"transliteration":{"text":"ish'raḥ","language_name":"english"}},{"id":27912,"position":4,"audio_url":"wbw/020_025_004.mp3","char_type_name":"word","text_qpc_hafs":"لِي","text_uthmani":"لِى","line_number":11,"text_uthmani_tajweed":"لِى","page_number":313,"text":"لِى","translation":{"text":"for me","language_name":"english"},"transliteration":{"text":"lī","language_name":"english"}},{"id":27913,"position":5,"audio_url":"wbw/020_025_005.mp3","char_type_name":"word","text_qpc_hafs":"صَدۡرِي","text_uthmani":"صَدْرِى","line_number":11,"text_uthmani_tajweed":"صَ<rule class=qalaqah>دۡ</rule>رِى","page_number":313,"text":"صَدْرِى","translation":{"text":"my breast","language_name":"english"},"transliteration":{"text":"ṣadrī","language_name":"english"}},{"id":27914,"position":6,"audio_url":null,"char_type_name":"end","text_qpc_hafs":"٢٥","text_uthmani":"٢٥","line_number":11,"text_uthmani_tajweed":"٢٥","page_number":313,"text":"٢٥","translation":{"text":"(25)","language_name":"english"},"transliteration":{"text":null,"language_name":"english"}}],"audio":{"url":"Alafasy/mp3/020025.mp3","segments":[[0,1,100,730],[1,2,740,1340],[2,3,1350,2030],[3,4,2040,2450],[4,5,2460,3520]]},"translations":[{"id":404076,"resource_id":85,"text":"Moses said, ‘Lord, lift up my heart"}]},{"id":2374,"verse_number":26,"verse_key":"20:26","hizb_number":32,"rub_el_hizb_number":125,"ruku_number":271,"manzil_number":4,"sajdah_number":null,"text_qpc_hafs":"وَيَسِّرۡ لِيٓ أَمۡرِي ٢٦","text_uthmani":"وَيَسِّرْ لِىٓ أَمْرِى","page_number":313,"juz_number":16,"words":[{"id":28873,"position":1,"audio_url":"wbw/020_026_001.mp3","char_type_name":"word","text_qpc_hafs":"وَيَسِّرۡ","text_uthmani":"وَيَسِّرْ","line_number":11,"text_uthmani_tajweed":"وَيَسِّرۡ","page_number":313,"text":"وَيَسِّرْ","translation":{"text":"And ease","language_name":"english"},"transliteration":{"text":"wayassir","language_name":"english"}},{"id":28874,"position":2,"audio_url":"wbw/020_026_002.mp3","char_type_name":"word","text_qpc_hafs":"لِيٓ","text_uthmani":"لِىٓ","line_number":11,"text_uthmani_tajweed":"ل<rule class=madda_obligatory_monfasel>ِىٓ</rule>","page_number":313,"text":"لِىٓ","translation":{"text":"for me","language_name":"english"},"transliteration":{"text":"lī","language_name":"english"}},{"id":28875,"position":3,"audio_url":"wbw/020_026_003.mp3","char_type_name":"word","text_qpc_hafs":"أَمۡرِي","text_uthmani":"أَمْرِى","line_number":11,"text_uthmani_tajweed":"أَمۡرِى","page_number":313,"text":"أَمْرِى","translation":{"text":"my task","language_name":"english"},"transliteration":{"text":"amrī","language_name":"english"}},{"id":28876,"position":4,"audio_url":null,"char_type_name":"end","text_qpc_hafs":"٢٦","text_uthmani":"٢٦","line_number":11,"text_uthmani_tajweed":"٢٦","page_number":313,"text":"٢٦","translation":{"text":"(26)","language_name":"english"},"transliteration":{"text":null,"language_name":"english"}}],"audio":{"url":"Alafasy/mp3/020026.mp3","segments":[[0,1,100,940],[1,2,950,3030],[2,3,3040,3800]]},"translations":[{"id":404077,"resource_id":85,"text":"and ease my task for me."}]},{"id":2375,"verse_number":27,"verse_key":"20:27","hizb_number":32,"rub_el_hizb_number":125,"ruku_number":271,"manzil_number":4,"sajdah_number":null,"text_qpc_hafs":"وَٱحۡلُلۡ عُقۡدَةٗ مِّن لِّسَانِي ٢٧","text_uthmani":"وَٱحْلُلْ عُقْدَةً مِّن لِّسَانِى","page_number":313,"juz_number":16,"words":[{"id":29664,"position":1,"audio_url":"wbw/020_027_001.mp3","char_type_name":"word","text_qpc_hafs":"وَٱحۡلُلۡ","text_uthmani":"وَٱحْلُلْ","line_number":11,"text_uthmani_tajweed":"وَ<rule class=ham_wasl>ٱ</rule>حۡلُلۡ","page_number":313,"text":"وَٱحْلُلْ","translation":{"text":"And untie","language_name":"english"},"transliteration":{"text":"wa-uḥ'lul","language_name":"english"}},{"id":29665,"position":2,"audio_url":"wbw/020_027_002.mp3","char_type_name":"word","text_qpc_hafs":"عُقۡدَةٗ","text_uthmani":"عُقْدَةًۭ","line_number":11,"text_uthmani_tajweed":"عُ<rule class=qalaqah>قۡ</rule>دَ<rule class=idgham_ghunnah>ةً</rule>","page_number":313,"text":"عُقْدَةًۭ","translation":{"text":"(the) knot","language_name":"english"},"transliteration":{"text":"ʿuq'datan","language_name":"english"}},{"id":29666,"position":3,"audio_url":"wbw/020_027_003.mp3","char_type_name":"word","text_qpc_hafs":"مِّن","text_uthmani":"مِّن","line_number":11,"text_uthmani_tajweed":"<rule class=idgham_ghunnah>م</rule>ّ<rule class=idgham_wo_ghunnah>ِن</rule>","page_number":313,"text":"مِّن","translation":{"text":"from","language_name":"english"},"transliteration":{"text":"min","language_name":"english"}},{"id":29667,"position":4,"audio_url":"wbw/020_027_004.mp3","char_type_name":"word","text_qpc_hafs":"لِّسَانِي","text_uthmani":"لِّسَانِى","line_number":12,"text_uthmani_tajweed":"<rule class=idgham_wo_ghunnah>ل</rule>ِّسَانِى","page_number":313,"text":"لِّسَانِى","translation":{"text":"my tongue","language_name":"english"},"transliteration":{"text":"lisānī","language_name":"english"}},{"id":29668,"position":5,"audio_url":null,"char_type_name":"end","text_qpc_hafs":"٢٧","text_uthmani":"٢٧","line_number":12,"text_uthmani_tajweed":"٢٧","page_number":313,"text":"٢٧","translation":{"text":"(27)","language_name":"english"},"transliteration":{"text":null,"language_name":"english"}}],"audio":{"url":"Alafasy/mp3/020027.mp3","segments":[[0,1,30,810],[1,2,820,2770],[2,3,2780,2910],[3,4,2920,4300]]},"translations":[{"id":404078,"resource_id":85,"text":"Untie my tongue,"}]},{"id":2376,"verse_number":28,"verse_key":"20:28","hizb_number":32,"rub_el_hizb_number":125,"ruku_number":271,"manzil_number":4,"sajdah_number":null,"text_qpc_hafs":"يَفۡقَهُواْ قَوۡلِي ٢٨","text_uthmani":"يَفْقَهُوا۟ قَوْلِى","page_number":313,"juz_number":16,"words":[{"id":30680,"position":1,"audio_url":"wbw/020_028_001.mp3","char_type_name":"word","text_qpc_hafs":"يَفۡقَهُواْ","text_uthmani":"يَفْقَهُوا۟","line_number":12,"text_uthmani_tajweed":"يَفۡقَهُو<rule class=slnt>اۡ</rule>","page_number":313,"text":"يَفْقَهُوا۟","translation":{"text":"That they may understand","language_name":"english"},"transliteration":{"text":"yafqahū","language_name":"english"}},{"id":30681,"position":2,"audio_url":"wbw/020_028_002.mp3","char_type_name":"word","text_qpc_hafs":"قَوۡلِي","text_uthmani":"قَوْلِى","line_number":12,"text_uthmani_tajweed":"قَوۡلِى","page_number":313,"text":"قَوْلِى","translation":{"text":"my speech","language_name":"english"},"transliteration":{"text":"qawlī","language_name":"english"}},{"id":30682,"position":3,"audio_url":null,"char_type_name":"end","text_qpc_hafs":"٢٨","text_uthmani":"٢٨","line_number":12,"text_uthmani_tajweed":"٢٨","page_number":313,"text":"٢٨","translation":{"text":"(28)","language_name":"english"},"transliteration":{"text":null,"language_name":"english"}}],"audio":{"url":"Alafasy/mp3/020028.mp3","segments":[[0,1,30,1000],[1,2,1010,2040]]},"translations":[{"id":404079,"resource_id":85,"text":"so that they may understand my words,"}]},{"id":2377,"verse_number":29,"verse_key":"20:29","hizb_number":32,"rub_el_hizb_number":125,"ruku_number":271,"manzil_number":4,"sajdah_number":null,"text_qpc_hafs":"وَٱجۡعَل لِّي وَزِيرٗا مِّنۡ أَهۡلِي ٢٩","text_uthmani":"وَٱجْعَل لِّى وَزِيرًا مِّنْ أَهْلِى","page_number":313,"juz_number":16,"words":[{"id":31804,"position":1,"audio_url":"wbw/020_029_001.mp3","char_type_name":"word","text_qpc_hafs":"وَٱجۡعَل","text_uthmani":"وَٱجْعَل","line_number":12,"text_uthmani_tajweed":"وَ<rule class=ham_wasl>ٱ</rule><rule class=qalaqah>جۡ</rule>عَل","page_number":313,"text":"وَٱجْعَل","translation":{"text":"And appoint","language_name":"english"},"transliteration":{"text":"wa-ij'ʿal","language_name":"english"}},{"id":31805,"position":2,"audio_url":"wbw/020_029_002.mp3","char_type_name":"word","text_qpc_hafs":"لِّي","text_uthmani":"لِّى","line_number":12,"text_uthmani_tajweed":"لِّى","page_number":313,"text":"لِّى","translation":{"text":"for me","language_name":"english"},"transliteration":{"text":"lī","language_name":"english"}},{"id":31806,"position":3,"audio_url":"wbw/020_029_003.mp3","char_type_name":"word","text_qpc_hafs":"وَزِيرٗا","text_uthmani":"وَزِيرًۭا","line_number":12,"text_uthmani_tajweed":"وَزِي<rule class=idgham_ghunnah>رًا</rule>","page_number":313,"text":"وَزِيرًۭا","translation":{"text":"a minister","language_name":"english"},"transliteration":{"text":"wazīran","language_name":"english"}},{"id":31807,"position":4,"audio_url":"wbw/020_029_004.mp3","char_type_name":"word","text_qpc_hafs":"مِّنۡ","text_uthmani":"مِّنْ","line_number":12,"text_uthmani_tajweed":"<rule class=idgham_ghunnah>م</rule>ِّنۡ","page_number":313,"text":"مِّنْ","translation":{"text":"from","language_name":"english"},"transliteration":{"text":"min","language_name":"english"}},{"id":31808,"position":5,"audio_url":"wbw/020_029_005.mp3","char_type_name":"word","text_qpc_hafs":"أَهۡلِي","text_uthmani":"أَهْلِى","line_number":12,"text_uthmani_tajweed":"أَهۡلِى","page_number":313,"text":"أَهْلِى","translation":{"text":"my family","language_name":"english"},"transliteration":{"text":"ahlī","language_name":"english"}},{"id":31809,"position":6,"audio_url":null,"char_type_name":"end","text_qpc_hafs":"٢٩","text_uthmani":"٢٩","line_number":12,"text_uthmani_tajweed":"٢٩","page_number":313,"text":"٢٩","translation":{"text":"(29)","language_name":"english"},"transliteration":{"text":null,"language_name":"english"}}],"audio":{"url":"Alafasy/mp3/020029.mp3","segments":[[0,1,30,760],[1,2,770,1260],[2,3,1270,2130],[3,4,2140,3380],[4,5,3390,4350]]},"translations":[{"id":404080,"resource_id":85,"text":"and give me a helper from my family,"}]},{"id":2378,"verse_number":30,"verse_key":"20:30","hizb_number":32,"rub_el_hizb_number":125,"ruku_number":271,"manzil_number":4,"sajdah_number":null,"text_qpc_hafs":"هَٰرُونَ أَخِي ٣٠","text_uthmani":"هَـٰرُونَ أَخِى","page_number":313,"juz_number":16,"words":[{"id":32871,"position":1,"audio_url":"wbw/020_030_001.mp3","char_type_name":"word","text_qpc_hafs":"هَٰرُونَ","text_uthmani":"هَـٰرُونَ","line_number":12,"text_uthmani_tajweed":"هَ<rule class=madda_normal>ـٰ</rule>رُونَ","page_number":313,"text":"هَـٰرُونَ","translation":{"text":"Harun","language_name":"english"},"transliteration":{"text":"hārūna","language_name":"english"}},{"id":32872,"position":2,"audio_url":"wbw/020_030_002.mp3","char_type_name":"word","text_qpc_hafs":"أَخِي","text_uthmani":"أَخِى","line_number":13,"text_uthmani_tajweed":"أَخِى","page_number":313,"text":"أَخِى","translation":{"text":"my brother","language_name":"english"},"transliteration":{"text":"akhī","language_name":"english"}},{"id":32873,"position":3,"audio_url":null,"char_type_name":"end","text_qpc_hafs":"٣٠","text_uthmani":"٣٠","line_number":13,"text_uthmani_tajweed":"٣٠","page_number":313,"text":"٣٠","translation":{"text":"(30)","language_name":"english"},"transliteration":{"text":null,"language_name":"english"}}],"audio":{"url":"Alafasy/mp3/020030.mp3","segments":[[0,1,50,1140],[1,2,1150,1930]]},"translations":[{"id":404081,"resource_id":85,"text":"my brother Aaron-"}]},{"id":2379,"verse_number":31,"verse_key":"20:31","hizb_number":32,"rub_el_hizb_number":125,"ruku_number":271,"manzil_number":4,"sajdah_number":null,"text_qpc_hafs":"ٱشۡدُدۡ بِهِۦٓ أَزۡرِي ٣١","text_uthmani":"ٱشْدُدْ بِهِۦٓ أَزْرِى","page_number":313,"juz_number":16,"words":[{"id":33532,"position":1,"audio_url":"wbw/020_031_001.mp3","char_type_name":"word","text_qpc_hafs":"ٱشۡدُدۡ","text_uthmani":"ٱشْدُدْ","line_number":13,"text_uthmani_tajweed":"ٱشۡدُ<rule class=qalaqah>دۡ</rule>","page_number":313,"text":"ٱشْدُدْ","translation":{"text":"Reinforce","language_name":"english"},"transliteration":{"text":"ush'dud","language_name":"english"}},{"id":33533,"position":2,"audio_url":"wbw/020_031_002.mp3","char_type_name":"word","text_qpc_hafs":"بِهِۦٓ","text_uthmani":"بِهِۦٓ","line_number":13,"text_uthmani_tajweed":"بِه<rule class=madda_obligatory_monfasel>ِۦٓ</rule>","page_number":313,"text":"بِهِۦٓ","translation":{"text":"through him","language_name":"english"},"transliteration":{"text":"bihi","language_name":"english"}},{"id":33534,"position":3,"audio_url":"wbw/020_031_003.mp3","char_type_name":"word","text_qpc_hafs":"أَزۡرِي","text_uthmani":"أَزْرِى","line_number":13,"text_uthmani_tajweed":"أَزۡرِى","page_number":313,"text":"أَزْرِى","translation":{"text":"my strength","language_name":"english"},"transliteration":{"text":"azrī","language_name":"english"}},{"id":33535,"position":4,"audio_url":null,"char_type_name":"end","text_qpc_hafs":"٣١","text_uthmani":"٣١","line_number":13,"text_uthmani_tajweed":"٣١","page_number":313,"text":"٣١","translation":{"text":"(31)","language_name":"english"},"transliteration":{"text":null,"language_name":"english"}}],"audio":{"url":"Alafasy/mp3/020031.mp3","segments":[[0,1,240,940],[1,2,950,2790],[2,3,2800,3590]]},"translations":[{"id":404082,"resource_id":85,"text":"augment my strength through him."}]},{"id":2380,"verse_number":32,"verse_key":"20:32","hizb_number":32,"rub_el_hizb_number":125,"ruku_number":271,"manzil_number":4,"sajdah_number":null,"text_qpc_hafs":"وَأَشۡرِكۡهُ فِيٓ أَمۡرِي ٣٢","text_uthmani":"وَأَشْرِكْهُ فِىٓ أَمْرِى","page_number":313,"juz_number":16,"words":[{"id":34606,"position":1,"audio_url":"wbw/020_032_001.mp3","char_type_name":"word","text_qpc_hafs":"وَأَشۡرِكۡهُ","text_uthmani":"وَأَشْرِكْهُ","line_number":13,"text_uthmani_tajweed":"وَأَشۡرِكۡهُ","page_number":313,"text":"وَأَشْرِكْهُ","translation":{"text":"And make him share","language_name":"english"},"transliteration":{"text":"wa-ashrik'hu","language_name":"english"}},{"id":34607,"position":2,"audio_url":"wbw/020_032_002.mp3","char_type_name":"word","text_qpc_hafs":"فِيٓ","text_uthmani":"فِىٓ","line_number":13,"text_uthmani_tajweed":"ف<rule class=madda_obligatory_monfasel>ِىٓ</rule>","page_number":313,"text":"فِىٓ","translation":{"text":"[in]","language_name":"english"},"transliteration":{"text":"fī","language_name":"english"}},{"id":34608,"position":3,"audio_url":"wbw/020_032_003.mp3","char_type_name":"word","text_qpc_hafs":"أَمۡرِي","text_uthmani":"أَمْرِى","line_number":13,"text_uthmani_tajweed":"أَمۡرِى","page_number":313,"text":"أَمْرِى","translation":{"text":"my task","language_name":"english"},"transliteration":{"text":"amrī","language_name":"english"}},{"id":34609,"position":4,"audio_url":null,"char_type_name":"end","text_qpc_hafs":"٣٢","text_uthmani":"٣٢","line_number":13,"text_uthmani_tajweed":"٣٢","page_number":313,"text":"٣٢","translation":{"text":"(32)","language_name":"english"},"transliteration":{"text":null,"language_name":"english"}}],"audio":{"url":"Alafasy/mp3/020032.mp3","segments":[[0,1,30,1230],[1,2,1240,3080],[2,3,3090,3920]]},"translations":[{"id":404083,"resource_id":85,"text":"Let him share my task"}]},{"id":2381,"verse_number":33,"verse_key":"20:33","hizb_number":32,"rub_el_hizb_number":125,"ruku_number":271,"manzil_number":4,"sajdah_number":null,"text_qpc_hafs":"كَيۡ نُسَبِّحَكَ كَثِيرٗا ٣٣","text_uthmani":"كَىْ نُسَبِّحَكَ كَثِيرًا","page_number":313,"juz_number":16,"words":[{"id":35417,"position":1,"audio_url":"wbw/020_033_001.mp3","char_type_name":"word","text_qpc_hafs":"كَيۡ","text_uthmani":"كَىْ","line_number":13,"text_uthmani_tajweed":"كَىۡ","page_number":313,"text":"كَىْ","translation":{"text":"That","language_name":"english"},"transliteration":{"text":"kay","language_name":"english"}},{"id":35418,"position":2,"audio_url":"wbw/020_033_002.mp3","char_type_name":"word","text_qpc_hafs":"نُسَبِّحَكَ","text_uthmani":"نُسَبِّحَكَ","line_number":13,"text_uthmani_tajweed":"نُسَبِّحَكَ","page_number":313,"text":"نُسَبِّحَكَ","translation":{"text":"we may glorify You","language_name":"english"},"transliteration":{"text":"nusabbiḥaka","language_name":"english"}},{"id":35419,"position":3,"audio_url":"wbw/020_033_003.mp3","char_type_name":"word","text_qpc_hafs":"كَثِيرٗا","text_uthmani":"كَثِيرًۭا","line_number":14,"text_uthmani_tajweed":"كَثِيرًا","page_number":313,"text":"كَثِيرًۭا","translation":{"text":"much","language_name":"english"},"transliteration":{"text":"kathīran","language_name":"english"}},{"id":35420,"position":4,"audio_url":null,"char_type_name":"end","text_qpc_hafs":"٣٣","text_uthmani":"٣٣","line_number":14,"text_uthmani_tajweed":"٣٣","page_number":313,"text":"٣٣","translation":{"text":"(33)","language_name":"english"},"transliteration":{"text":null,"language_name":"english"}}],"audio":{"url":"Alafasy/mp3/020033.mp3","segments":[[0,1,40,250],[1,2,260,1760],[2,3,1770,3080]]},"translations":[{"id":404084,"resource_id":85,"text":"so that we can glorify You much"}]},{"id":2382,"verse_number":34,"verse_key":"20:34","hizb_number":32,"rub_el_hizb_number":125,"ruku_number":271,"manzil_number":4,"sajdah_number":null,"text_qpc_hafs":"وَنَذۡكُرَكَ كَثِيرًا ٣٤","text_uthmani":"وَنَذْكُرَكَ كَثِيرًا","page_number":313,"juz_number":16,"words":[{"id":36346,"position":1,"audio_url":"wbw/020_034_001.mp3","char_type_name":"word","text_qpc_hafs":"وَنَذۡكُرَكَ","text_uthmani":"وَنَذْكُرَكَ","line_number":14,"text_uthmani_tajweed":"وَنَذۡكُرَكَ","page_number":313,"text":"وَنَذْكُرَكَ","translation":{"text":"And [we] remember You","language_name":"english"},"transliteration":{"text":"wanadhkuraka","language_name":"english"}},{"id":36347,"position":2,"audio_url":"wbw/020_034_002.mp3","char_type_name":"word","text_qpc_hafs":"كَثِيرًا","text_uthmani":"كَثِيرًا","line_number":14,"text_uthmani_tajweed":"كَثِيرًا","page_number":313,"text":"كَثِيرًا","translation":{"text":"much","language_name":"english"},"transliteration":{"text":"kathīran","language_name":"english"}},{"id":36348,"position":3,"audio_url":null,"char_type_name":"end","text_qpc_hafs":"٣٤","text_uthmani":"٣٤","line_number":14,"text_uthmani_tajweed":"٣٤","page_number":313,"text":"٣٤","translation":{"text":"(34)","language_name":"english"},"transliteration":{"text":null,"language_name":"english"}}],"audio":{"url":"Alafasy/mp3/020034.mp3","segments":[[0,1,100,1350],[1,2,1360,2660]]},"translations":[{"id":404085,"resource_id":85,"text":"and remember You often:"}]},{"id":2383,"verse_number":35,"verse_key":"20:35","hizb_number":32,"rub_el_hizb_number":125,"ruku_number":271,"manzil_number":4,"sajdah_number":null,"text_qpc_hafs":"إِنَّكَ كُنتَ بِنَا بَصِيرٗا ٣٥","text_uthmani":"إِنَّكَ كُنتَ بِنَا بَصِيرًا","page_number":313,"juz_number":16,"words":[{"id":37163,"position":1,"audio_url":"wbw/020_035_001.mp3","char_type_name":"word","text_qpc_hafs":"إِنَّكَ","text_uthmani":"إِنَّكَ","line_number":14,"text_uthmani_tajweed":"إِ<rule class=ghunnah>نّ</rule>َكَ","page_number":313,"text":"إِنَّكَ","translation":{"text":"Indeed, [You]","language_name":"english"},"transliteration":{"text":"innaka","language_name":"english"}},{"id":37164,"position":2,"audio_url":"wbw/020_035_002.mp3","char_type_name":"word","text_qpc_hafs":"كُنتَ","text_uthmani":"كُنتَ","line_number":14,"text_uthmani_tajweed":"كُ<rule class=ikhafa>نت</rule>َ","page_number":313,"text":"كُنتَ","translation":{"text":"You are","language_name":"english"},"transliteration":{"text":"kunta","language_name":"english"}},{"id":37165,"position":3,"audio_url":"wbw/020_035_003.mp3","char_type_name":"word","text_qpc_hafs":"بِنَا","text_uthmani":"بِنَا","line_number":14,"text_uthmani_tajweed":"بِنَا","page_number":313,"text":"بِنَا","translation":{"text":"of us","language_name":"english"},"transliteration":{"text":"binā","language_name":"english"}},{"id":37166,"position":4,"audio_url":"wbw/020_035_004.mp3","char_type_name":"word","text_qpc_hafs":"بَصِيرٗا","text_uthmani":"بَصِيرًۭا","line_number":14,"text_uthmani_tajweed":"بَصِيرًا","page_number":313,"text":"بَصِيرًۭا","translation":{"text":"All-Seer","language_name":"english"},"transliteration":{"text":"baṣīran","language_name":"english"}},{"id":37167,"position":5,"audio_url":null,"char_type_name":"end","text_qpc_hafs":"٣٥","text_uthmani":"٣٥","line_number":14,"text_uthmani_tajweed":"٣٥","page_number":313,"text":"٣٥","translation":{"text":"(35)","language_name":"english"},"transliteration":{"text":null,"language_name":"english"}}],"audio":{"url":"Alafasy/mp3/020035.mp3","segments":[[0,1,40,1380],[1,2,1390,2850],[2,3,2860,3520],[3,4,3530,4830]]},"translations":[{"id":404086,"resource_id":85,"text":"You are always watching over us.’"}]},{"id":2384,"verse_number":36,"verse_key":"20:36","hizb_number":32,"rub_el_hizb_number":125,"ruku_number":271,"manzil_number":4,"sajdah_number":null,"text_qpc_hafs":"قَالَ قَدۡ أُوتِيتَ سُؤۡلَكَ يَٰمُوسَىٰ ٣٦","text_uthmani":"قَالَ قَدْ أُوتِيتَ سُؤْلَكَ يَـٰمُوسَىٰ","page_number":313,"juz_number":16,"words":[{"id":37966,"position":1,"audio_url":"wbw/020_036_001.mp3","char_type_name":"word","text_qpc_hafs":"قَالَ","text_uthmani":"قَالَ","line_number":14,"text_uthmani_tajweed":"قَالَ","page_number":313,"text":"قَالَ","translation":{"text":"He said","language_name":"english"},"transliteration":{"text":"qāla","language_name":"english"}},{"id":37967,"position":2,"audio_url":"wbw/020_036_002.mp3","char_type_name":"word","text_qpc_hafs":"قَدۡ","text_uthmani":"قَدْ","line_number":14,"text_uthmani_tajweed":"قَ<rule class=qalaqah>دۡ</rule>","page_number":313,"text":"قَدْ","translation":{"text":"Verily","language_name":"english"},"transliteration":{"text":"qad","language_name":"english"}},{"id":37968,"position":3,"audio_url":"wbw/020_036_003.mp3","char_type_name":"word","text_qpc_hafs":"أُوتِيتَ","text_uthmani":"أُوتِيتَ","line_number":15,"text_uthmani_tajweed":"أُوتِيتَ","page_number":313,"text":"أُوتِيتَ","translation":{"text":"you are granted","language_name":"english"},"transliteration":{"text":"ūtīta","language_name":"english"}},{"id":37969,"position":4,"audio_url":"wbw/020_036_004.mp3","char_type_name":"word","text_qpc_hafs":"سُؤۡلَكَ","text_uthmani":"سُؤْلَكَ","line_number":15,"text_uthmani_tajweed":"سُؤۡلَكَ","page_number":313,"text":"سُؤْلَكَ","translation":{"text":"your request","language_name":"english"},"transliteration":{"text":"su'laka","language_name":"english"}},{"id":37970,"position":5,"audio_url":"wbw/020_036_005.mp3","char_type_name":"word","text_qpc_hafs":"يَٰمُوسَىٰ","text_uthmani":"يَـٰمُوسَىٰ","line_number":15,"text_uthmani_tajweed":"يَ<rule class=madda_normal>ـٰ</rule>مُوسَىٰ","page_number":313,"text":"يَـٰمُوسَىٰ","translation":{"text":"O Musa","language_name":"english"},"transliteration":{"text":"yāmūsā","language_name":"english"}},{"id":37971,"position":6,"audio_url":null,"char_type_name":"end","text_qpc_hafs":"٣٦","text_uthmani":"٣٦","line_number":15,"text_uthmani_tajweed":"٣٦","page_number":313,"text":"٣٦","translation":{"text":"(36)","language_name":"english"},"transliteration":{"text":null,"language_name":"english"}}],"audio":{"url":"Alafasy/mp3/020036.mp3","segments":[[0,1,40,630],[1,2,640,1120],[2,3,1130,2190],[3,4,2200,3180],[4,5,3190,4990]]},"translations":[{"id":404087,"resource_id":85,"text":"God said, ‘Moses, your request is granted."}]},{"id":2385,"verse_number":37,"verse_key":"20:37","hizb_number":32,"rub_el_hizb_number":125,"ruku_number":271,"manzil_number":4,"sajdah_number":null,"text_qpc_hafs":"وَلَقَدۡ مَنَنَّا عَلَيۡكَ مَرَّةً أُخۡرَىٰٓ ٣٧","text_uthmani":"وَلَقَدْ مَنَنَّا عَلَيْكَ مَرَّةً أُخْرَىٰٓ","page_number":313,"juz_number":16,"words":[{"id":38799,"position":1,"audio_url":"wbw/020_037_001.mp3","char_type_name":"word","text_qpc_hafs":"وَلَقَدۡ","text_uthmani":"وَلَقَدْ","line_number":15,"text_uthmani_tajweed":"وَلَقَ<rule class=qalaqah>دۡ</rule>","page_number":313,"text":"وَلَقَدْ","translation":{"text":"And indeed","language_name":"english"},"transliteration":{"text":"walaqad","language_name":"english"}},{"id":38800,"position":2,"audio_url":"wbw/020_037_002.mp3","char_type_name":"word","text_qpc_hafs":"مَنَنَّا","text_uthmani":"مَنَنَّا","line_number":15,"text_uthmani_tajweed":"مَنَ<rule class=ghunnah>نّ</rule>َا","page_number":313,"text":"مَنَنَّا","translation":{"text":"We conferred a favor","language_name":"english"},"transliteration":{"text":"manannā","language_name":"english"}},{"id":38801,"position":3,"audio_url":"wbw/020_037_003.mp3","char_type_name":"word","text_qpc_hafs":"عَلَيۡكَ","text_uthmani":"عَلَيْكَ","line_number":15,"text_uthmani_tajweed":"عَلَيۡكَ","page_number":313,"text":"عَلَيْكَ","translation":{"text":"on you","language_name":"english"},"transliteration":{"text":"ʿalayka","language_name":"english"}},{"id":38802,"position":4,"audio_url":"wbw/020_037_004.mp3","char_type_name":"word","text_qpc_hafs":"مَرَّةً","text_uthmani":"مَرَّةً","line_number":15,"text_uthmani_tajweed":"مَرَّةً","page_number":313,"text":"مَرَّةً","translation":{"text":"another time","language_name":"english"},"transliteration":{"text":"marratan","language_name":"english"}},{"id":38803,"position":5,"audio_url":"wbw/020_037_005.mp3","char_type_name":"word","text_qpc_hafs":"أُخۡرَىٰٓ","text_uthmani":"أُخْرَىٰٓ","line_number":15,"text_uthmani_tajweed":"أُخۡرَىٰٓ","page_number":313,"text":"أُخْرَىٰٓ","translation":{"text":"another time","language_name":"english"},"transliteration":{"text":"ukh'rā","language_name":"english"}},{"id":38804,"position":6,"audio_url":null,"char_type_name":"end","text_qpc_hafs":"٣٧","text_uthmani":"٣٧","line_number":15,"text_uthmani_tajweed":"٣٧","page_number":313,"text":"٣٧","translation":{"text":"(37)","language_name":"english"},"transliteration":{"text":null,"language_name":"english"}}],"audio":{"url":"Alafasy/mp3/020037.mp3","segments":[[0,1,30,850],[1,2,860,2700],[2,3,2710,3680],[3,4,3690,4800],[4,5,4810,5880]]},"translations":[{"id":404088,"resource_id":85,"text":"Indeed We showed you favour before."}]}]